	<resource id='1001464' type='accessory'>
		<![CDATA[1001464.1002622.1000857.1000955.group=Interior]]>
		<![CDATA[1001464.1000851.1000858.1000947.description=Tough and flexible, the all-weather cargo mat is uniquely designed to fit, enabling you to carry all types of cargo without worrying about soils and stains. It features a skid-resistant surface to help contain spills.<br><br><i>Cargo and load capacity limited by weight and distribution.</i>]]>
		<![CDATA[1001464.1002622.1000865.1000988.option=false]]>
		<![CDATA[1001464.1000851.1000856.1000937.derived=false]]>
		<![CDATA[1001464.1000851.1000859.1000875.msrp=100.00]]>
		<![CDATA[1001464.1000851.1000856.1000938.videokey=]]>
		<![CDATA[1001464.1002622.1000865.1000980.source=NVS]]>
		<![CDATA[1001464.1002622.1000865.1000987.group=Interior]]>
		<![CDATA[1001464.1002622.1000857.1000953.alacarte=true]]>
		<![CDATA[1001464.1000851.1000859.1000875.derived=false]]>
		<![CDATA[1001464.1002622.1000859.1000878.specialexteriorcolorflag=false]]>
		<![CDATA[1001464.1000851.1000857.1000953.title=Cargo Liner]]>
		<![CDATA[1001464.1000851.1000856.1000938.title=All Weather Cargo Mat [installed_msrp]]]>
		<![CDATA[1001464.1000851.1000857.1000948.msrp=100.00]]>
		<![CDATA[1001464.1000851.1000856.1000937.specialexteriorcolorflag=false]]>
		<![CDATA[1001464.1000851.1000865.1000983.derived=false]]>
		<![CDATA[1001464.1000851.1000857.1000950.description=Tough and flexible, the cargo liner enables you to carry all types of items while helping protect your cargo area carpeting<br>&bull; Made of tough, easy-to-clean material and features a Toyota logo<br>&bull; Skid-resistant surface helps keep items in place<br>&bull; Attaches to third row seatbacks allowing seats to be adjusted independently<br>&bull; Available in black, gray and almond]]>
		<![CDATA[1001464.1002622.1000857.1000956.alacarte=true]]>
		<![CDATA[1001464.1000851.1000865.1000983.source=NVS]]>
		<![CDATA[1001464.1000851.1000856.1000936.videokey=]]>
		<![CDATA[1001464.group=Interior]]>
		<![CDATA[1001464.1000851.1000865.1000986.derived=false]]>
		<![CDATA[1001464.1000851.1000857.title=Cargo Liner [installed_msrp]]]>
		<![CDATA[1001464.1002622.1000858.1000947.keyfeatures=]]>
		<![CDATA[1001464.1002622.1000857.1000953.description=Available in black, gray or almond, the cargo liner helps you carry all types of items and protect your cargo area carpeting.<br>• Tough, easy-to-clean material is embossed with a Toyota logo and features a skid-resistant surface that helps keep items in place<br>• The cargo liner attaches to third-row seatbacks, allowing seats to be adjusted independently]]>
		<![CDATA[1001464.1002622.1000865.1000980.secondaryfeatures=]]>
		<![CDATA[1001464.1002622.1000869.1000918.vtc=false]]>
		<![CDATA[1001464.1000851.1000865.1000983.msrp=105.00]]>
		<![CDATA[1001464.1000851.1000865.1000980.title=All Weather Cargo Mat]]>
		<![CDATA[1001464.1000851.1000856.1000936.marketingeffectivedate=]]>
		<![CDATA[1001464.1000851.1000857.1000952.derived=false]]>
		<![CDATA[1001464.1000851.1000869.1000920.title=All Weather Mat - Cargo Mat]]>
		<![CDATA[1001464.1000851.1000869.1000915.description=The all-weather cargo mat helps protect the cargo area from premature wear and tear.<br>&bull;Made of tough, easy-to-clean material and featuring a sculpted Venza logo<br>&bull;Skid-resistant surface helps keep items in place&bull;Designed for an exact fit to your Venza’s cargo area<br><br><i>Cargo and load capacity are limited by weight and distribution. </i>]]>
		<![CDATA[1001464.1002622.1000858.1000947.specialinteriorcolorflag=false]]>
		<![CDATA[1001464.1000851.1000865.title=All-Weather Cargo Mat [installed_msrp]]]>
		<![CDATA[1001464.1002622.1000859.1000876.msrp=100]]>
		<![CDATA[1001464.1002622.1000865.1000986.msrp=105]]>
		<![CDATA[1001464.1002622.1000857.1000951.specialinteriorcolorflag=false]]>
		<![CDATA[1001464.1000851.1000865.1000985.description=The all-weather cargo mat helps protect the cargo area from premature wear and tear.<br>&bull; Made of tough, easy-to-clean material featuring an embossed Sequoia logo<br>&bull; Skid-resistant surface helps keep items in place<br>&bull; Designed for an exact fit to your Sequoia’s cargo area<br><br><i>Cargo and load capacity are limited by weight and distribution.</i>]]>
		<![CDATA[1001464.1000851.1000857.1000952.description=Tough and flexible, the cargo liner enables you to carry all types of items while helping protect your cargo area carpeting<br>&bull; Made of tough, easy-to-clean material and features a Toyota logo<br>&bull; Skid-resistant surface helps keep items in place<br>&bull; Attaches to third row seatbacks allowing seats to be adjusted independently<br>&bull; Available in black, gray and almond]]>
		<![CDATA[1001464.1000851.1000869.1000916.msrp=100.00]]>
		<![CDATA[1001464.1000851.1000857.1000959.description=Tough and flexible, the cargo liner enables you to carry all types of items while helping protect your cargo area carpeting<br>&bull; Made of tough, easy-to-clean material and features a Toyota logo<br>&bull; Skid-resistant surface helps keep items in place<br>&bull; Attaches to third row seatbacks allowing seats to be adjusted independently<br>&bull; Available in black, gray and almond]]>
		<![CDATA[1001464.1002622.1000865.1000983.specialinteriorcolorflag=false]]>
		<![CDATA[1001464.1002622.1000857.1000949.alacarte=true]]>
		<![CDATA[1001464.1000851.1000856.1000937.secondaryfeatures=]]>
		<![CDATA[1001464.1002622.1000869.1000912.marketingeffectivedate=]]>
		<![CDATA[1001464.1000851.1000857.1000959.title=Cargo Liner]]>
		<![CDATA[1001464.1000851.1000869.1000917.group=Interior]]>
		<![CDATA[1001464.1002622.1000865.1000981.description=The tough, flexible all- weather cargo mat allows you to carry a wide variety of items and helps protect your cargo area carpeting.<br>• Made of durable, easy-to-clean material embossed with a Sequoia logo<br>• Skid-resistant surface helps secure items in place]]>
		<![CDATA[1001464.1002622.1000865.1000986.specialinteriorcolorflag=false]]>
		<![CDATA[1001464.1002622.1000859.1000877.msrp=100]]>
		<![CDATA[1001464.1002622.1000865.1000980.option=false]]>
		<![CDATA[1001464.1002622.1000859.1003292.source=NVS]]>
		<![CDATA[1001464.1000851.1000858.1000947.specialinteriorcolorflag=false]]>
		<![CDATA[1001464.1000851.1000869.1000913.derived=false]]>
		<![CDATA[1001464.1002622.1000869.1000921.msrp=100.00]]>
		<![CDATA[1001464.1002622.1000869.1000916.title=All-Weather Floor Mat and  Cargo Mat]]>
		<![CDATA[1001464.1002622.1000865.1000982.specialinteriorcolorflag=false]]>
		<![CDATA[1001464.1002622.1000857.1000954.specialinteriorcolorflag=false]]>
		<![CDATA[1001464.1002622.1000857.1000948.package=false]]>
		<![CDATA[1001464.1002622.1000869.1000916.source=NVS]]>
		<![CDATA[1001464.1000851.1000865.1000982.source=NVS]]>
		<![CDATA[1001464.1002622.1000869.1000919.package=false]]>
		<![CDATA[1001464.1000851.1000858.viewpointkey=]]>
		<![CDATA[1001464.1000851.1000856.1000936.specialinteriorcolorflag=false]]>
		<![CDATA[1001464.1000851.1000869.1000914.msrp=100.00]]>
		<![CDATA[1001464.1002622.1000869.1000917.alacarte=true]]>
		<![CDATA[1001464.1002622.1000865.1000981.derived=true]]>
		<![CDATA[1001464.1002622.1000865.1000983.group=Interior]]>
		<![CDATA[1001464.1000851.1000857.1000960.description=Tough and flexible, the cargo liner enables you to carry all types of items while helping protect your cargo area carpeting<br>&bull; Made of tough, easy-to-clean material and features a Toyota logo<br>&bull; Skid-resistant surface helps keep items in place<br>&bull; Attaches to third row seatbacks allowing seats to be adjusted independently<br>&bull; Available in black, gray and almond]]>
		<![CDATA[1001464.1002622.1000865.1000985.source=NVS]]>
		<![CDATA[1001464.1000851.1000859.1000876.msrp=100.00]]>
		<![CDATA[1001464.1002622.1000857.1000951.source=NVS]]>
		<![CDATA[1001464.1002622.1000869.1000914.msrp=100.00]]>
		<![CDATA[1001464.1000851.1000865.1000985.msrp=105.00]]>
		<![CDATA[1001464.1000851.1000869.1000920.msrp=100.00]]>
		<![CDATA[1001464.1002622.1000859.1000875.source=NVS]]>
		<![CDATA[1001464.1002622.1000857.1000949.source=NVS]]>
		<![CDATA[1001464.1002622.1000857.1000952.derived=false]]>
		<![CDATA[1001464.1002622.1000869.1000919.source=NVS]]>
		<![CDATA[1001464.1000851.1000856.1000936.viewpointkey=]]>
		<![CDATA[1001464.1002622.1000859.1003292.option=false]]>
		<![CDATA[1001464.1002622.1000865.1000987.derived=true]]>
		<![CDATA[1001464.1002622.1000865.1000983.alacarte=true]]>
		<![CDATA[1001464.1002622.1000869.1000912.viewpointkey=]]>
		<![CDATA[1001464.1000851.1000869.1000918.msrp=100.00]]>
		<![CDATA[1001464.1000851.1000857.1000951.source=NVS]]>
		<![CDATA[1001464.1002622.1000859.1000877.derived=false]]>
		<![CDATA[1001464.1002622.1000857.1000957.specialinteriorcolorflag=false]]>
		<![CDATA[1001464.1002622.1000857.1000958.source=NVS]]>
		<![CDATA[1001464.1002622.1000865.1000985.alacarte=true]]>
		<![CDATA[1001464.1000851.1000865.1000988.title=All Weather Cargo Mat]]>
		<![CDATA[1001464.1000851.1000865.1000981.description=The all-weather cargo mat helps protect the cargo area from premature wear and tear.<br>&bull; Made of tough, easy-to-clean material featuring an embossed Sequoia logo<br>&bull; Skid-resistant surface helps keep items in place<br>&bull; Designed for an exact fit to your Sequoia’s cargo area<br><br><i>Cargo and load capacity are limited by weight and distribution.</i>]]>
		<![CDATA[1001464.1000851.1000857.1000955.description=Tough and flexible, the cargo liner enables you to carry all types of items while helping protect your cargo area carpeting<br>&bull; Made of tough, easy-to-clean material and features a Toyota logo<br>&bull; Skid-resistant surface helps keep items in place<br>&bull; Attaches to third row seatbacks allowing seats to be adjusted independently<br>&bull; Available in black, gray and almond]]>
		<![CDATA[1001464.1000851.1000857.1000951.title=Cargo Liner]]>
		<![CDATA[1001464.1000851.1000857.1000959.derived=false]]>
		<![CDATA[1001464.1002622.1000869.1000921.alacarte=true]]>
		<![CDATA[1001464.1002622.1000857.1000955.source=NVS]]>
		<![CDATA[1001464.1000851.1000856.1000938.secondaryfeatures=]]>
		<![CDATA[1001464.1000851.1000869.1000916.vtc=true]]>
		<![CDATA[1001464.vtc=true]]>
		<![CDATA[1001464.1000851.1000869.1000914.title=All Weather Mat - Cargo Mat]]>
		<![CDATA[1001464.1000851.1000865.1000987.description=The all-weather cargo mat helps protect the cargo area from premature wear and tear.<br>&bull; Made of tough, easy-to-clean material featuring an embossed Sequoia logo<br>&bull; Skid-resistant surface helps keep items in place<br>&bull; Designed for an exact fit to your Sequoia’s cargo area<br><br><i>Cargo and load capacity are limited by weight and distribution.</i>]]>
		<![CDATA[1001464.1002622.1000865.1000980.videokey=]]>
		<![CDATA[1001464.1002622.1000865.1000984.title=All Weather Cargo Mat [installed_msrp]]]>
		<![CDATA[1001464.1002622.1000865.1000984.package=false]]>
		<![CDATA[1001464.1000851.1000856.1000936.description=An essential accessory to accompany you on your adventures, this custom-fitted cargo tray helps keep your cargo area clean and dry:<br />•Cut to an exact fit of your FJ’s cargo area<br />•Multidimensional surface and perimeter lip help contain dirt, debris and liquids<br />•Molded FJ logo adds a touch of customization<br /><br /><em>Cargo load and capacity limited by weight and distribution.</em>ion.]]>
		<![CDATA[1001464.1000851.1000858.1000947.marketingeffectivedate=]]>
		<![CDATA[1001464.1000851.1000865.1000986.title=All Weather Cargo Mat]]>
		<![CDATA[1001464.1002622.1000857.1000949.package=false]]>
		<![CDATA[1001464.1000851.1000858.group=Interior]]>
		<![CDATA[1001464.1000851.1000869.1000919.vtc=true]]>
		<![CDATA[1001464.1002622.1000857.1000954.description=Available in black, gray or almond, the cargo liner helps you carry all types of items and protect your cargo area carpeting.<br>• Tough, easy-to-clean material is embossed with a Toyota logo and features a skid-resistant surface that helps keep items in place<br>• The cargo liner attaches to third-row seatbacks, allowing seats to be adjusted independently]]>
		<![CDATA[1001464.1002622.1000857.1000948.specialinteriorcolorflag=false]]>
		<![CDATA[1001464.1000851.1000869.1000917.alacarte=true]]>
		<![CDATA[1001464.1002622.1000857.1000949.title=Cargo Liner  [installed_msrp]]]>
		<![CDATA[1001464.1000851.1000857.1000948.source=NVS]]>
		<![CDATA[1001464.1002622.1000857.1000957.specialexteriorcolorflag=false]]>
		<![CDATA[1001464.1002622.1000857.1000951.derived=false]]>
		<![CDATA[1001464.1000851.1000857.1000956.source=NVS]]>
		<![CDATA[1001464.1000851.1000869.1000919.description=The all-weather cargo mat helps protect the cargo area from premature wear and tear.<br>&bull;Made of tough, easy-to-clean material and featuring a sculpted Venza logo<br>&bull;Skid-resistant surface helps keep items in place&bull;Designed for an exact fit to your Venza’s cargo area<br><br><i>Cargo and load capacity are limited by weight and distribution. </i>]]>
		<![CDATA[1001464.1002622.1000857.1000949.specialexteriorcolorflag=false]]>
		<![CDATA[1001464.1002622.1000857.1000960.source=NVS]]>
		<![CDATA[1001464.1002622.1000857.1000948.source=NVS]]>
		<![CDATA[1001464.1000851.1000857.1000948.description=Tough and flexible, the cargo liner enables you to carry all types of items while helping protect your cargo area carpeting<br>&bull; Made of tough, easy-to-clean material and features a Toyota logo<br>&bull; Skid-resistant surface helps keep items in place<br>&bull; Attaches to third row seatbacks allowing seats to be adjusted independently<br>&bull; Available in black, gray and almond]]>
		<![CDATA[1001464.1000851.1000858.1000947.keyfeatures=]]>
		<![CDATA[1001464.1002622.1000859.1000878.title=All-Weather Cargo Mat  [installed_msrp]]]>
		<![CDATA[1001464.1000851.1000869.1000912.description=The all-weather cargo mat helps protect the cargo area from premature wear and tear.<br>&bull;Made of tough, easy-to-clean material and featuring a sculpted Venza logo<br>&bull;Skid-resistant surface helps keep items in place&bull;Designed for an exact fit to your Venza’s cargo area<br><br><i>Cargo and load capacity are limited by weight and distribution. </i>]]>
		<![CDATA[1001464.1000851.1000865.1000988.description=The all-weather cargo mat helps protect the cargo area from premature wear and tear.<br>&bull; Made of tough, easy-to-clean material featuring an embossed Sequoia logo<br>&bull; Skid-resistant surface helps keep items in place<br>&bull; Designed for an exact fit to your Sequoia’s cargo area<br><br><i>Cargo and load capacity are limited by weight and distribution.</i>]]>
		<![CDATA[1001464.1002622.1000858.1000947.package=false]]>
		<![CDATA[1001464.1002622.1000859.1000875.derived=false]]>
		<![CDATA[1001464.1002622.1000865.1000980.description=The tough, flexible all- weather cargo mat allows you to carry a wide variety of items and helps protect your cargo area carpeting.<br>• Made of durable, easy-to-clean material embossed with a Sequoia logo<br>• Skid-resistant surface helps secure items in place]]>
		<![CDATA[1001464.1002622.1000858.1000947.msrp=105]]>
		<![CDATA[1001464.1002622.1000858.1000947.secondaryfeatures=]]>
		<![CDATA[1001464.1002622.1000869.1000912.vtc=false]]>
		<![CDATA[1001464.1000851.1000856.1000938.marketingeffectivedate=]]>
		<![CDATA[1001464.1000851.1000857.1000951.description=Tough and flexible, the cargo liner enables you to carry all types of items while helping protect your cargo area carpeting<br>&bull; Made of tough, easy-to-clean material and features a Toyota logo<br>&bull; Skid-resistant surface helps keep items in place<br>&bull; Attaches to third row seatbacks allowing seats to be adjusted independently<br>&bull; Available in black, gray and almond]]>
		<![CDATA[1001464.1000851.1000865.1000983.description=The all-weather cargo mat helps protect the cargo area from premature wear and tear.<br>&bull; Made of tough, easy-to-clean material featuring an embossed Sequoia logo<br>&bull; Skid-resistant surface helps keep items in place<br>&bull; Designed for an exact fit to your Sequoia’s cargo area<br><br><i>Cargo and load capacity are limited by weight and distribution.</i>]]>
		<![CDATA[1001464.1002622.1000858.1000947.description=The tough, flexible all- weather cargo mat allows you to carry a wide variety of items and helps protect your cargo area carpeting.<br>• Made of durable, easy-to-clean material embossed with a Land Cruiser logo<br>• Skid-resistant surface helps secure items in place ]]>
		<![CDATA[1001464.1002622.1000859.1000875.specialexteriorcolorflag=false]]>
		<![CDATA[1001464.1002622.1000869.1000914.derived=false]]>
		<![CDATA[1001464.1000851.1000856.1000936.title=All Weather Cargo Mat [installed_msrp]]]>
		<![CDATA[1001464.1000851.1000859.1000877.description=Tough and flexible, the cargo mat helps protect your cargo area carpeting when transporting all types of items. <br>&bull; Made of tough, easy-to-clean material<br>&bull; Skid-resistant surface helps keep items in place<br>&bull; Designed for an exact fit to the cargo area<br>&bull; Features an embossed Prius logo]]>
		<![CDATA[1001464.1000851.1000869.1000919.source=NVS]]>
		<![CDATA[1001464.1000851.1000856.1000936.source=NVS]]>
		<![CDATA[1001464.1002622.1000865.1000985.derived=true]]>
		<![CDATA[1001464.1002622.1000857.1000957.option=false]]>
		<![CDATA[1001464.1002622.1000857.1000949.description=Available in black, gray or almond, the cargo liner helps you carry all types of items and protect your cargo area carpeting.<br>• Tough, easy-to-clean material is embossed with a Toyota logo and features a skid-resistant surface that helps keep items in place<br>• The cargo liner attaches to third-row seatbacks, allowing seats to be adjusted independently]]>
		<![CDATA[1001464.1002622.1000865.1000984.alacarte=true]]>
		<![CDATA[1001464.1002622.1000865.1000985.specialexteriorcolorflag=false]]>
		<![CDATA[1001464.1002622.1000865.1000982.source=NVS]]>
		<![CDATA[1001464.1002622.1000857.1000952.specialexteriorcolorflag=false]]>
		<![CDATA[1001464.1002622.1000859.1000876.package=false]]>
		<![CDATA[1001464.1000851.1000857.1000957.description=Tough and flexible, the cargo liner enables you to carry all types of items while helping protect your cargo area carpeting<br>&bull; Made of tough, easy-to-clean material and features a Toyota logo<br>&bull; Skid-resistant surface helps keep items in place<br>&bull; Attaches to third row seatbacks allowing seats to be adjusted independently<br>&bull; Available in black, gray and almond]]>
		<![CDATA[1001464.1002622.1000865.1000980.specialinteriorcolorflag=false]]>
		<![CDATA[1001464.1002622.1000865.1000988.specialexteriorcolorflag=false]]>
		<![CDATA[1001464.1000851.1000856.1000936.keyfeatures=]]>
		<![CDATA[1001464.1002622.1000857.1000960.specialexteriorcolorflag=false]]>
		<![CDATA[1001464.1000851.1000857.1000949.derived=false]]>
		<![CDATA[1001464.1000851.1000857.1000949.msrp=100.00]]>
		<![CDATA[1001464.1002622.1000857.1000951.option=false]]>
		<![CDATA[1001464.1002622.1000858.1000947.option=false]]>
		<![CDATA[1001464.1002622.1000857.1000959.option=false]]>
		<![CDATA[1001464.1002622.1000865.1000985.title=All Weather Cargo Mat [installed_msrp]]]>
		<![CDATA[1001464.1000851.1000859.alacarte=true]]>
		<![CDATA[1001464.1000851.1000857.1000958.source=NVS]]>
		<![CDATA[1001464.1000851.1000859.1000877.title=All Weather Cargo Mat]]>
		<![CDATA[1001464.1002622.1000857.1000954.group=Interior]]>
		<![CDATA[1001464.1002622.1000859.1000878.group=Interior]]>
		<![CDATA[1001464.1000851.1000857.1000955.derived=false]]>
		<![CDATA[1001464.1002622.1000857.1000950.description=Available in black, gray or almond, the cargo liner helps you carry all types of items and protect your cargo area carpeting.<br>• Tough, easy-to-clean material is embossed with a Toyota logo and features a skid-resistant surface that helps keep items in place<br>• The cargo liner attaches to third-row seatbacks, allowing seats to be adjusted independently]]>
		<![CDATA[1001464.1002622.1000869.1000919.msrp=100.00]]>
		<![CDATA[1001464.1000851.1000869.1000917.vtc=true]]>
		<![CDATA[1001464.1002622.1000865.1000987.option=false]]>
		<![CDATA[1001464.1002622.1000865.1000982.group=Interior]]>
		<![CDATA[1001464.1002622.1000857.1000953.group=Interior]]>
		<![CDATA[1001464.1000851.1000857.1000954.msrp=100.00]]>
		<![CDATA[1001464.1002622.1000869.1000916.package=false]]>
		<![CDATA[1001464.1000851.1000857.1000959.source=NVS]]>
		<![CDATA[1001464.1002622.1000857.1000955.derived=false]]>
		<![CDATA[1001464.1000851.1000865.1000980.source=NVS]]>
		<![CDATA[1001464.1002622.1000857.1000954.msrp=100]]>
		<![CDATA[1001464.1000851.1000857.1000953.derived=false]]>
		<![CDATA[1001464.1000851.1000865.1000984.derived=false]]>
		<![CDATA[1001464.1002622.1000857.1000954.specialexteriorcolorflag=false]]>
		<![CDATA[1001464.1002622.1000857.1000953.title=Cargo Liner  [installed_msrp]]]>
		<![CDATA[1001464.1000851.1000857.1000956.msrp=100.00]]>
		<![CDATA[1001464.1002622.1000869.1000917.msrp=100.00]]>
		<![CDATA[1001464.1000851.1000865.1000984.source=NVS]]>
		<![CDATA[1001464.1002622.1000858.1000947.pnglayeringinclusionkey=]]>
		<![CDATA[1001464.1000851.1000856.1000938.specialexteriorcolorflag=false]]>
		<![CDATA[1001464.1002622.1000857.1000955.description=Available in black, gray or almond, the cargo liner helps you carry all types of items and protect your cargo area carpeting.<br>• Tough, easy-to-clean material is embossed with a Toyota logo and features a skid-resistant surface that helps keep items in place<br>• The cargo liner attaches to third-row seatbacks, allowing seats to be adjusted independently]]>
		<![CDATA[1001464.1002622.1000865.1000987.msrp=105]]>
		<![CDATA[1001464.1002622.1000857.1000949.specialinteriorcolorflag=false]]>
		<![CDATA[1001464.1002622.1000857.1000960.msrp=100]]>
		<![CDATA[1001464.1000851.1000856.1000938.pnglayeringinclusionkey=]]>
		<![CDATA[1001464.1002622.1000858.1000947.videokey=]]>
		<![CDATA[1001464.1002622.1000857.1000953.source=NVS]]>
		<![CDATA[1001464.1000851.1000856.1000937.pnglayeringinclusionkey=]]>
		<![CDATA[1001464.1002622.1000869.1000912.option=false]]>
		<![CDATA[1001464.1000851.1000864.alacarte=true]]>
		<![CDATA[1001464.1000851.1000857.1000948.title=Cargo Liner]]>
		<![CDATA[1001464.1002622.1000857.1000950.title=Cargo Liner  [installed_msrp]]]>
		<![CDATA[1001464.1002622.1000865.1000983.source=NVS]]>
		<![CDATA[1001464.1002622.1000859.1003292.alacarte=true]]>
		<![CDATA[1001464.1000851.1000858.marketingeffectivedate=]]>
		<![CDATA[1001464.1002622.1000857.1000948.title=Cargo Liner  [installed_msrp]]]>
		<![CDATA[1001464.1000851.1000865.1000980.derived=false]]>
		<![CDATA[1001464.1000851.1000859.1000878.description=Tough and flexible, the cargo mat helps protect your cargo area carpeting when transporting all types of items. <br>&bull; Made of tough, easy-to-clean material<br>&bull; Skid-resistant surface helps keep items in place<br>&bull; Designed for an exact fit to the cargo area<br>&bull; Features an embossed Prius logo]]>
		<![CDATA[1001464.1002622.1000857.1000948.keyfeatures=]]>
		<![CDATA[1001464.1000851.1000859.group=Interior]]>
		<![CDATA[1001464.1000851.1000869.1000921.alacarte=true]]>
		<![CDATA[1001464.1002622.1000865.1000980.derived=true]]>
		<![CDATA[1001464.1000851.1000857.1000949.source=NVS]]>
		<![CDATA[1001464.1002622.1000869.1000912.description=]]>
		<![CDATA[1001464.1000851.1000869.1000915.msrp=100.00]]>
		<![CDATA[1001464.1002622.1000865.1000988.description=The tough, flexible all- weather cargo mat allows you to carry a wide variety of items and helps protect your cargo area carpeting.<br>• Made of durable, easy-to-clean material embossed with a Sequoia logo<br>• Skid-resistant surface helps secure items in place]]>
		<![CDATA[1001464.1002622.1000857.1000951.msrp=100]]>
		<![CDATA[1001464.1000851.1000857.1000955.title=Cargo Liner]]>
		<![CDATA[1001464.1002622.1000857.1000956.specialexteriorcolorflag=false]]>
		<![CDATA[1001464.1002622.1000859.1000875.marketingeffectivedate=]]>
		<![CDATA[1001464.1002622.1000865.1000983.package=false]]>
		<![CDATA[1001464.1000851.1000857.1000950.title=Cargo Liner]]>
		<![CDATA[1001464.1000851.1000856.1000936.derived=false]]>
		<![CDATA[1001464.1000851.1000869.1000915.source=NVS]]>
		<![CDATA[1001464.1000851.1000865.1000980.description=The all-weather cargo mat helps protect the cargo area from premature wear and tear.<br>&bull; Made of tough, easy-to-clean material featuring an embossed Sequoia logo<br>&bull; Skid-resistant surface helps keep items in place<br>&bull; Designed for an exact fit to your Sequoia’s cargo area<br><br><i>Cargo and load capacity are limited by weight and distribution.</i>]]>
		<![CDATA[1001464.1002622.1000869.1000916.alacarte=true]]>
		<![CDATA[1001464.1000851.1000869.1000920.group=Interior]]>
		<![CDATA[1001464.1000851.1000869.1000917.msrp=100.00]]>
		<![CDATA[1001464.1000851.1000856.alacarte=true]]>
		<![CDATA[1001464.1002622.1000865.1000985.msrp=105]]>
		<![CDATA[1001464.1002622.1000857.1000958.derived=false]]>
		<![CDATA[1001464.1000851.1000869.1000913.source=NVS]]>
		<![CDATA[1001464.1000851.1000865.1000985.source=NVS]]>
		<![CDATA[1001464.1002622.1000859.1003292.package=false]]>
		<![CDATA[1001464.1000851.1000869.1000921.description=The all-weather cargo mat helps protect the cargo area from premature wear and tear.<br>&bull;Made of tough, easy-to-clean material and featuring a sculpted Venza logo<br>&bull;Skid-resistant surface helps keep items in place&bull;Designed for an exact fit to your Venza’s cargo area<br><br><i>Cargo and load capacity are limited by weight and distribution. </i>]]>
		<![CDATA[1001464.1002622.1000859.1000876.alacarte=true]]>
		<![CDATA[1001464.1002622.1000857.1000957.group=Interior]]>
		<![CDATA[1001464.1002622.1000869.1000914.alacarte=true]]>
		<![CDATA[1001464.1002622.1000857.1000948.viewpointkey=]]>
		<![CDATA[1001464.1002622.1000857.1000953.msrp=100]]>
		<![CDATA[1001464.1000851.1000856.1000937.marketingeffectivedate=]]>
		<![CDATA[1001464.1002622.1000869.1000914.source=NVS]]>
		<![CDATA[1001464.1002622.1000857.1000952.title=Cargo Liner  [installed_msrp]]]>
		<![CDATA[1001464.1002622.1000859.1000877.specialinteriorcolorflag=false]]>
		<![CDATA[1001464.1002622.1000857.1000958.description=Available in black, gray or almond, the cargo liner helps you carry all types of items and protect your cargo area carpeting.<br>• Tough, easy-to-clean material is embossed with a Toyota logo and features a skid-resistant surface that helps keep items in place<br>• The cargo liner attaches to third-row seatbacks, allowing seats to be adjusted independently]]>
		<![CDATA[1001464.1002622.1000869.1000912.alacarte=true]]>
		<![CDATA[1001464.1002622.1000857.1000957.derived=false]]>
		<![CDATA[1001464.1002622.1000869.1000912.title=All Weather Mat - Cargo Mat]]>
		<![CDATA[1001464.1002622.1000865.1000981.specialexteriorcolorflag=false]]>
		<![CDATA[1001464.1002622.1000865.1000981.option=false]]>
		<![CDATA[1001464.1000851.1000858.1000947.title=All Weather Cargo Mat (1 pc)]]>
		<![CDATA[1001464.1000851.1000856.1000937.description=An essential accessory to accompany you on your adventures, this custom-fitted cargo tray helps keep your cargo area clean and dry:<br />•Cut to an exact fit of your FJ’s cargo area<br />•Multidimensional surface and perimeter lip help contain dirt, debris and liquids<br />•Molded FJ logo adds a touch of customization<br /><br /><em>Cargo load and capacity limited by weight and distribution.</em>ion.]]>
		<![CDATA[1001464.1000851.1000857.group=Interior]]>
		<![CDATA[1001464.1002622.1000857.1000960.title=Cargo Liner  [installed_msrp]]]>
		<![CDATA[1001464.1002622.1000859.1000876.group=Interior]]>
		<![CDATA[1001464.1002622.1000865.1000986.alacarte=true]]>
		<![CDATA[1001464.1002622.1000865.1000980.group=Interior]]>
		<![CDATA[1001464.1002622.1000865.1000986.source=NVS]]>
		<![CDATA[1001464.1000851.1000865.1000986.description=The all-weather cargo mat helps protect the cargo area from premature wear and tear.<br>&bull; Made of tough, easy-to-clean material featuring an embossed Sequoia logo<br>&bull; Skid-resistant surface helps keep items in place<br>&bull; Designed for an exact fit to your Sequoia’s cargo area<br><br><i>Cargo and load capacity are limited by weight and distribution.</i>]]>
		<![CDATA[1001464.1002622.1000857.1000960.alacarte=true]]>
		<![CDATA[1001464.1002622.1000865.1000986.specialexteriorcolorflag=false]]>
		<![CDATA[1001464.1002622.1000859.1000876.description=The tough, flexible all- weather cargo mat allows you to carry a wide variety of items and helps protect your cargo area carpeting.<br>• Made of durable, easy-to-clean material embossed with a Prius logo<br>• Skid-resistant surface helps secure items in place]]>
		<![CDATA[1001464.1002622.1000859.1000878.source=NVS]]>
		<![CDATA[1001464.1000851.1000856.1000938.source=NVS]]>
		<![CDATA[1001464.1000851.1000869.1000918.group=Interior]]>
		<![CDATA[1001464.1000851.1000858.1000947.specialexteriorcolorflag=false]]>
		<![CDATA[1001464.1000851.1000857.1000958.description=Tough and flexible, the cargo liner enables you to carry all types of items while helping protect your cargo area carpeting<br>&bull; Made of tough, easy-to-clean material and features a Toyota logo<br>&bull; Skid-resistant surface helps keep items in place<br>&bull; Attaches to third row seatbacks allowing seats to be adjusted independently<br>&bull; Available in black, gray and almond]]>
		<![CDATA[1001464.1002622.1000865.1000986.group=Interior]]>
		<![CDATA[1001464.1000851.1000865.1000981.derived=false]]>
		<![CDATA[1001464.1002622.1000865.1000988.title=All Weather Cargo Mat [installed_msrp]]]>
		<![CDATA[1001464.1002622.1000857.1000959.specialexteriorcolorflag=false]]>
		<![CDATA[1001464.1002622.1000865.1000980.msrp=105]]>
		<![CDATA[1001464.1002622.1000859.1000875.description=The tough, flexible all- weather cargo mat allows you to carry a wide variety of items and helps protect your cargo area carpeting.<br>• Made of durable, easy-to-clean material embossed with a Prius logo<br>• Skid-resistant surface helps secure items in place]]>
		<![CDATA[1001464.1002622.1000857.1000956.group=Interior]]>
		<![CDATA[1001464.1000851.1000856.1000936.option=false]]>
		<![CDATA[1001464.1002622.1000865.1000984.source=NVS]]>
		<![CDATA[1001464.1000851.1000858.1000947.secondaryfeatures=]]>
		<![CDATA[1001464.1000851.1000865.1000981.title=All Weather Cargo Mat]]>
		<![CDATA[1001464.1002622.1000859.1000875.group=Interior]]>
		<![CDATA[1001464.1000851.1000856.1000938.derived=false]]>
		<![CDATA[1001464.1002622.1000857.1000949.derived=false]]>
		<![CDATA[1001464.1002622.1000859.1000875.pnglayeringinclusionkey=]]>
		<![CDATA[1001464.1000851.1000869.1000912.alacarte=true]]>
		<![CDATA[1001464.1000851.1000869.1000914.vtc=true]]>
		<![CDATA[1001464.1000851.1000859.1000878.title=All Weather Cargo Mat]]>
		<![CDATA[1001464.1002622.1000859.1000875.keyfeatures=]]>
		<![CDATA[1001464.1000851.1000869.1000913.description=The all-weather cargo mat helps protect the cargo area from premature wear and tear.<br>&bull;Made of tough, easy-to-clean material and featuring a sculpted Venza logo<br>&bull;Skid-resistant surface helps keep items in place&bull;Designed for an exact fit to your Venza’s cargo area<br><br><i>Cargo and load capacity are limited by weight and distribution. </i>]]>
		<![CDATA[1001464.1002622.1000859.1000875.option=false]]>
		<![CDATA[1001464.1002622.1000857.1000952.package=false]]>
		<![CDATA[1001464.1002622.1000857.1000950.alacarte=true]]>
		<![CDATA[1001464.1002622.1000869.1000916.msrp=100.00]]>
		<![CDATA[1001464.1000851.1000865.group=Interior]]>
		<![CDATA[1001464.1002622.1000857.1000953.derived=false]]>
		<![CDATA[1001464.1000851.1000869.1000915.title=All Weather Mat - Cargo Mat]]>
		<![CDATA[1001464.1002622.1000869.1000912.group=]]>
		<![CDATA[1001464.1000851.1000865.1000985.title=All-Weather Cargo Mat [installed_msrp]]]>
		<![CDATA[1001464.1002622.1000857.1000959.title=Cargo Liner  [installed_msrp]]]>
		<![CDATA[1001464.1000851.1000858.title=All-Weather Cargo Mat [installed_msrp]]]>
		<![CDATA[1001464.1002622.1000859.1003292.description=The tough, flexible all- weather cargo mat allows you to carry a wide variety of items and helps protect your cargo area carpeting.<br>• Made of durable, easy-to-clean material embossed with a Prius logo<br>• Skid-resistant surface helps secure items in place]]>
		<![CDATA[1001464.1002622.1000857.1000960.specialinteriorcolorflag=false]]>
		<![CDATA[1001464.1002622.1000857.1000959.description=Available in black, gray or almond, the cargo liner helps you carry all types of items and protect your cargo area carpeting.<br>• Tough, easy-to-clean material is embossed with a Toyota logo and features a skid-resistant surface that helps keep items in place<br>• The cargo liner attaches to third-row seatbacks, allowing seats to be adjusted independently]]>
		<![CDATA[1001464.1000851.1000856.1000938.package=false]]>
		<![CDATA[1001464.1000851.1000869.1000918.title=All Weather Mat - Cargo Mat]]>
		<![CDATA[1001464.1002622.1000865.1000982.msrp=105]]>
		<![CDATA[1001464.1002622.1000857.1000957.title=Cargo Liner  [installed_msrp]]]>
		<![CDATA[1001464.1002622.1000865.1000984.group=Interior]]>
		<![CDATA[1001464.1002622.1000857.1000952.alacarte=true]]>
		<![CDATA[1001464.1002622.1000857.1000951.package=false]]>
		<![CDATA[1001464.1000851.1000856.1000936.package=false]]>
		<![CDATA[1001464.1000851.1000864.derived=false]]>
		<![CDATA[1001464.1000851.1000865.1000987.derived=false]]>
		<![CDATA[1001464.1002622.1000857.1000953.specialexteriorcolorflag=false]]>
		<![CDATA[1001464.1000851.1000857.1000949.description=Tough and flexible, the cargo liner enables you to carry all types of items while helping protect your cargo area carpeting<br>&bull; Made of tough, easy-to-clean material and features a Toyota logo<br>&bull; Skid-resistant surface helps keep items in place<br>&bull; Attaches to third row seatbacks allowing seats to be adjusted independently<br>&bull; Available in black, gray and almond]]>
		<![CDATA[1001464.1000851.1000869.1000919.msrp=100.00]]>
		<![CDATA[1001464.1002622.1000869.1000918.package=false]]>
		<![CDATA[1001464.1002622.1000865.1000980.viewpointkey=]]>
		<![CDATA[1001464.1000851.1000858.1000947.derived=false]]>
		<![CDATA[1001464.1002622.1000857.1000948.videokey=]]>
		<![CDATA[1001464.1002622.1000865.1000985.package=false]]>
		<![CDATA[1001464.1002622.1000869.1000912.derived=false]]>
		<![CDATA[1001464.1000851.1000865.1000984.msrp=105.00]]>
		<![CDATA[1001464.1002622.1000857.1000958.group=Interior]]>
		<![CDATA[1001464.1002622.1000865.1000981.source=NVS]]>
		<![CDATA[1001464.1002622.1000857.1000957.alacarte=true]]>
		<![CDATA[1001464.1002622.1000865.1000984.msrp=105]]>
		<![CDATA[1001464.1002622.1000857.1000955.specialexteriorcolorflag=false]]>
		<![CDATA[1001464.1002622.1000859.1003292.msrp=100]]>
		<![CDATA[1001464.1002622.1000865.1000984.specialinteriorcolorflag=false]]>
		<![CDATA[1001464.1002622.1000859.1000877.alacarte=true]]>
		<![CDATA[1001464.1002622.1000865.1000983.description=The tough, flexible all- weather cargo mat allows you to carry a wide variety of items and helps protect your cargo area carpeting.<br>• Made of durable, easy-to-clean material embossed with a Sequoia logo<br>• Skid-resistant surface helps secure items in place]]>
		<![CDATA[1001464.1000851.1000857.1000959.msrp=100.00]]>
		<![CDATA[1001464.1002622.1000865.1000980.pnglayeringinclusionkey=]]>
		<![CDATA[1001464.1000851.1000869.1000912.title=All Weather Mat - Cargo Mat]]>
		<![CDATA[1001464.1002622.1000865.1000988.alacarte=true]]>
		<![CDATA[1001464.1000851.1000859.1000876.title=All Weather Cargo Mat]]>
		<![CDATA[1001464.1000851.1000857.1000957.source=NVS]]>
		<![CDATA[1001464.1000851.1000865.1000984.description=The all-weather cargo mat helps protect the cargo area from premature wear and tear.<br>&bull; Made of tough, easy-to-clean material featuring an embossed Sequoia logo<br>&bull; Skid-resistant surface helps keep items in place<br>&bull; Designed for an exact fit to your Sequoia’s cargo area<br><br><i>Cargo and load capacity are limited by weight and distribution.</i>]]>
		<![CDATA[1001464.1002622.1000869.1000912.package=false]]>
		<![CDATA[1001464.1000851.1000869.1000917.derived=false]]>
		<![CDATA[1001464.1000851.1000864.vtc=true]]>
		<![CDATA[1001464.1002622.1000857.1000960.group=Interior]]>
		<![CDATA[1001464.1000851.1000857.1000956.title=Cargo Liner]]>
		<![CDATA[1001464.1000851.1000869.1000913.msrp=100.00]]>
		<![CDATA[1001464.1002622.1000859.1000876.title=All-Weather Cargo Mat  [installed_msrp]]]>
		<![CDATA[1001464.1002622.1000865.1000983.specialexteriorcolorflag=false]]>
		<![CDATA[1001464.1002622.1000859.1000878.derived=false]]>
		<![CDATA[1001464.1002622.1000869.1000912.secondaryfeatures=]]>
		<![CDATA[1001464.1002622.1000857.1000952.group=Interior]]>
		<![CDATA[1001464.1002622.1000857.1000957.msrp=100]]>
		<![CDATA[1001464.1002622.1000857.1000948.specialexteriorcolorflag=false]]>
		<![CDATA[1001464.1000851.1000865.alacarte=true]]>
		<![CDATA[1001464.1000851.1000858.pnglayeringinclusionkey=]]>
		<![CDATA[1001464.1002622.1000865.1000980.title=All Weather Cargo Mat [installed_msrp]]]>
		<![CDATA[1001464.1000851.1000856.1000938.msrp=100.00]]>
		<![CDATA[1001464.1002622.1000857.1000952.specialinteriorcolorflag=false]]>
		<![CDATA[1001464.1002622.1000859.1003292.specialexteriorcolorflag=false]]>
		<![CDATA[1001464.1002622.1000857.1000953.specialinteriorcolorflag=false]]>
		<![CDATA[1001464.1002622.1000865.1000982.title=All Weather Cargo Mat [installed_msrp]]]>
		<![CDATA[1001464.1002622.1000865.1000983.msrp=105]]>
		<![CDATA[1001464.1002622.1000865.1000981.specialinteriorcolorflag=false]]>
		<![CDATA[1001464.1000851.1000869.1000912.derived=false]]>
		<![CDATA[1001464.1000851.1000856.group=Interior]]>
		<![CDATA[1001464.1002622.1000857.1000949.option=false]]>
		<![CDATA[1001464.1000851.1000856.1000936.msrp=100.00]]>
		<![CDATA[1001464.1000851.1000858.keyfeatures=]]>
		<![CDATA[1001464.1002622.1000857.1000954.title=Cargo Liner  [installed_msrp]]]>
		<![CDATA[1001464.1002622.1000857.1000955.alacarte=true]]>
		<![CDATA[1001464.1002622.1000858.1000947.source=NVS]]>
		<![CDATA[1001464.1002622.1000865.1000987.package=false]]>
		<![CDATA[1001464.1002622.1000857.1000950.specialexteriorcolorflag=false]]>
		<![CDATA[1001464.1000851.1000869.1000920.vtc=true]]>
		<![CDATA[1001464.1002622.1000857.1000953.package=false]]>
		<![CDATA[1001464.1002622.1000858.1000947.marketingeffectivedate=]]>
		<![CDATA[1001464.1000851.1000869.1000920.alacarte=true]]>
		<![CDATA[1001464.1000851.1000865.1000981.msrp=105.00]]>
		<![CDATA[1001464.1000851.1000869.1000919.alacarte=true]]>
		<![CDATA[1001464.1002622.1000859.1000875.specialinteriorcolorflag=false]]>
		<![CDATA[1001464.1002622.1000869.1000914.vtc=false]]>
		<![CDATA[1001464.1000851.1000858.vtc=true]]>
		<![CDATA[1001464.1000851.1000865.1000982.description=The all-weather cargo mat helps protect the cargo area from premature wear and tear.<br>&bull; Made of tough, easy-to-clean material featuring an embossed Sequoia logo<br>&bull; Skid-resistant surface helps keep items in place<br>&bull; Designed for an exact fit to your Sequoia’s cargo area<br><br><i>Cargo and load capacity are limited by weight and distribution.</i>]]>
		<![CDATA[1001464.1000851.1000856.1000937.videokey=]]>
		<![CDATA[1001464.1002622.1000857.1000950.derived=false]]>
		<![CDATA[1001464.1000851.1000859.1000876.derived=false]]>
		<![CDATA[1001464.1000851.1000865.1000985.derived=false]]>
		<![CDATA[1001464.1002622.1000865.1000988.source=NVS]]>
		<![CDATA[1001464.1000851.1000857.1000952.msrp=100.00]]>
		<![CDATA[1001464.1002622.1000869.1000919.alacarte=true]]>
		<![CDATA[1001464.1000851.1000856.1000938.keyfeatures=]]>
		<![CDATA[1001464.1000851.1000865.1000984.title=All Weather Cargo Mat]]>
		<![CDATA[1001464.1000851.1000859.1000877.source=NVS]]>
		<![CDATA[1001464.1000851.1000865.vtc=true]]>
		<![CDATA[1001464.1002622.1000869.1000921.package=false]]>
		<![CDATA[1001464.1002622.1000865.1000980.specialexteriorcolorflag=false]]>
		<![CDATA[1001464.1002622.1000857.1000958.msrp=100]]>
		<![CDATA[1001464.1002622.1000857.1000957.source=NVS]]>
		<![CDATA[1001464.1002622.1000865.1000988.group=Interior]]>
		<![CDATA[1001464.1000851.1000859.vtc=true]]>
		<![CDATA[1001464.1002622.1000859.1000878.package=false]]>
		<![CDATA[1001464.1002622.1000865.1000983.derived=true]]>
		<![CDATA[1001464.1000851.1000857.1000960.msrp=100.00]]>
		<![CDATA[1001464.1000851.1000865.1000982.title=All-Weather Cargo Mat [installed_msrp]]]>
		<![CDATA[1001464.1002622.1000865.1000980.package=false]]>
		<![CDATA[1001464.1002622.1000857.1000948.description=Available in black, gray or almond, the cargo liner helps you carry all types of items and protect your cargo area carpeting.<br>• Tough, easy-to-clean material is embossed with a Toyota logo and features a skid-resistant surface that helps keep items in place<br>• The cargo liner attaches to third-row seatbacks, allowing seats to be adjusted independently]]>
		<![CDATA[1001464.1002622.1000857.1000956.source=NVS]]>
		<![CDATA[1001464.1000851.1000865.1000986.source=NVS]]>
		<![CDATA[1001464.1002622.1000865.1000980.keyfeatures=]]>
		<![CDATA[1001464.1002622.1000857.1000958.specialexteriorcolorflag=false]]>
		<![CDATA[1001464.1000851.1000858.1000947.option=false]]>
		<![CDATA[1001464.1002622.1000857.1000948.pnglayeringinclusionkey=]]>
		<![CDATA[1001464.1002622.1000857.1000955.package=false]]>
		<![CDATA[1001464.1002622.1000857.1000952.msrp=100]]>
		<![CDATA[1001464.1000851.1000869.1000913.title=All Weather Mat - Cargo Mat]]>
		<![CDATA[1001464.1000851.1000856.1000937.package=false]]>
		<![CDATA[1001464.1002622.1000858.1000947.title=All Weather Cargo Mat  [installed_msrp]]]>
		<![CDATA[1001464.1002622.1000857.1000960.option=false]]>
		<![CDATA[1001464.1000851.1000858.1000947.package=false]]>
		<![CDATA[1001464.1000851.1000859.title=All-Weather Cargo Mat [installed_msrp]]]>
		<![CDATA[1001464.1002622.1000857.1000958.alacarte=true]]>
		<![CDATA[1001464.1002622.1000865.1000987.specialinteriorcolorflag=false]]>
		<![CDATA[1001464.1000851.1000864.description=Help protect your Toyota’s original factory carpet with a set of durable, all-weather mats.   The mats feature a ribbed channel design that helps contain moisture, dirt and other debris. Retention clips (on the driver's side) and nibbed backing on all mats help hold them in position.<br><br><i>To avoid interference with pedal operation: Each mat must be secured with retention hooks (clips). Do not install a floor mat on top of an existing floor mat. This floor mat was designed specifically for use in this model and model year vehicle and SHOULD NOT be used in any other vehicle.</i>]]>
		<![CDATA[1001464.1002622.1000865.1000982.derived=true]]>
		<![CDATA[1001464.1000851.1000857.1000954.source=NVS]]>
		<![CDATA[1001464.1002622.1000857.1000957.description=Available in black, gray or almond, the cargo liner helps you carry all types of items and protect your cargo area carpeting.<br>• Tough, easy-to-clean material is embossed with a Toyota logo and features a skid-resistant surface that helps keep items in place<br>• The cargo liner attaches to third-row seatbacks, allowing seats to be adjusted independently]]>
		<![CDATA[1001464.1002622.1000865.1000981.group=Interior]]>
		<![CDATA[1001464.1002622.1000858.1000947.derived=false]]>
		<![CDATA[1001464.1002622.1000865.1000988.package=false]]>
		<![CDATA[1001464.1000851.1000857.vtc=true]]>
		<![CDATA[1001464.1000851.1000858.1000947.videokey=]]>
		<![CDATA[1001464.1000851.1000857.1000960.source=NVS]]>
		<![CDATA[1001464.1000851.1000869.1000917.source=NVS]]>
		<![CDATA[1001464.1002622.1000865.1000985.option=false]]>
		<![CDATA[1001464.1000851.1000869.1000916.alacarte=true]]>
		<![CDATA[1001464.1002622.1000865.1000986.package=false]]>
		<![CDATA[1001464.1000851.1000864.title=All-Weather Floor Mats ]]>
		<![CDATA[1001464.1000851.1000869.1000917.title=All Weather Mat - Cargo Mat]]>
		<![CDATA[1001464.1002622.1000857.1000956.specialinteriorcolorflag=false]]>
		<![CDATA[1001464.1002622.1000865.1000984.specialexteriorcolorflag=false]]>
		<![CDATA[1001464.1002622.1000858.1000947.alacarte=true]]>
		<![CDATA[1001464.1000851.1000858.1000947.source=NVS]]>
		<![CDATA[1001464.1002622.1000857.1000956.option=false]]>
		<![CDATA[1001464.1000851.1000858.1000947.viewpointkey=]]>
		<![CDATA[1001464.1000851.1000857.1000957.derived=false]]>
		<![CDATA[1001464.1000851.1000869.1000916.source=NVS]]>
		<![CDATA[1001464.1000851.1000856.description=An essential accessory to accompany you on your adventures, this custom-fitted cargo tray helps keep your cargo area clean and dry:<br>&bull;Cut to an exact fit of your FJ’s cargo area<br>&bull;Multidimensional surface and perimeter lip help contain dirt, debris and liquids<br>&bull;Molded FJ logo adds a touch of customization<br><br><i>Cargo load and capacity limited by weight and distribution.</i>ion.]]>
		<![CDATA[1001464.1002622.1000859.1000875.secondaryfeatures=]]>
		<![CDATA[1001464.1002622.1000857.1000959.package=false]]>
		<![CDATA[1001464.1000851.1000857.1000955.source=NVS]]>
		<![CDATA[1001464.1000851.1000869.1000914.derived=false]]>
		<![CDATA[1001464.1000851.1000865.1000988.source=NVS]]>
		<![CDATA[1001464.1002622.1000869.1000919.title=All-Weather Floor Mat and  Cargo Mat]]>
		<![CDATA[1001464.1002622.1000857.1000953.option=false]]>
		<![CDATA[1001464.1000851.1000857.1000949.title=Cargo Liner]]>
		<![CDATA[1001464.1002622.1000869.1000912.videokey=]]>
		<![CDATA[1001464.1000851.1000869.1000913.vtc=true]]>
		<![CDATA[1001464.1002622.1000857.1000952.description=Available in black, gray or almond, the cargo liner helps you carry all types of items and protect your cargo area carpeting.<br>• Tough, easy-to-clean material is embossed with a Toyota logo and features a skid-resistant surface that helps keep items in place<br>• The cargo liner attaches to third-row seatbacks, allowing seats to be adjusted independently]]>
		<![CDATA[1001464.1002622.1000857.1000960.description=Available in black, gray or almond, the cargo liner helps you carry all types of items and protect your cargo area carpeting.<br>• Tough, easy-to-clean material is embossed with a Toyota logo and features a skid-resistant surface that helps keep items in place<br>• The cargo liner attaches to third-row seatbacks, allowing seats to be adjusted independently]]>
		<![CDATA[1001464.1002622.1000857.1000955.msrp=100]]>
		<![CDATA[1001464.1002622.1000865.1000982.package=false]]>
		<![CDATA[1001464.1000851.1000865.1000987.msrp=105]]>
		<![CDATA[1001464.1000851.1000856.1000937.option=false]]>
		<![CDATA[1001464.1000851.1000858.1000947.msrp=105.00]]>
		<![CDATA[1001464.1002622.1000857.1000951.title=Cargo Liner  [installed_msrp]]]>
		<![CDATA[1001464.1002622.1000869.1000921.title=All-Weather Floor Mat and  Cargo Mat]]>
		<![CDATA[1001464.1002622.1000859.1000877.description=The tough, flexible all- weather cargo mat allows you to carry a wide variety of items and helps protect your cargo area carpeting.<br>• Made of durable, easy-to-clean material embossed with a Prius logo<br>• Skid-resistant surface helps secure items in place]]>
		<![CDATA[1001464.1000851.1000857.1000958.derived=false]]>
		<![CDATA[1001464.1002622.1000859.1003292.title=All-Weather Cargo Mat  [installed_msrp]]]>
		<![CDATA[1001464.1002622.1000857.1000958.option=false]]>
		<![CDATA[1001464.1000851.1000857.1000948.derived=false]]>
		<![CDATA[1001464.1002622.1000865.1000981.title=All Weather Cargo Mat [installed_msrp]]]>
		<![CDATA[1001464.1000851.1000869.1000920.source=NVS]]>
		<![CDATA[1001464.1000851.1000856.1000937.source=NVS]]>
		<![CDATA[1001464.1000851.1000856.1000936.pnglayeringinclusionkey=]]>
		<![CDATA[1001464.1002622.1000859.1000878.description=The tough, flexible all- weather cargo mat allows you to carry a wide variety of items and helps protect your cargo area carpeting.<br>• Made of durable, easy-to-clean material embossed with a Prius logo<br>• Skid-resistant surface helps secure items in place]]>
		<![CDATA[1001464.1000851.1000857.1000950.source=NVS]]>
		<![CDATA[1001464.1000851.1000857.1000955.msrp=100.00]]>
		<![CDATA[1001464.1002622.1000859.1003292.group=Interior]]>
		<![CDATA[1001464.1002622.1000865.1000987.source=NVS]]>
		<![CDATA[1001464.1002622.1000859.1000876.specialexteriorcolorflag=false]]>
		<![CDATA[1001464.1002622.1000857.1000948.alacarte=true]]>
		<![CDATA[1001464.1000851.1000869.1000912.msrp=100.00]]>
		<![CDATA[1001464.1000851.1000869.1000912.source=NVS]]>
		<![CDATA[1001464.1002622.1000859.1000877.option=false]]>
		<![CDATA[1001464.1002622.1000859.1000878.specialinteriorcolorflag=false]]>
		<![CDATA[1001464.1000851.1000865.1000986.msrp=105.00]]>
		<![CDATA[1001464.1002622.1000865.1000982.specialexteriorcolorflag=false]]>
		<![CDATA[1001464.1000851.1000865.1000987.source=NVS]]>
		<![CDATA[1001464.1000851.1000869.1000921.vtc=true]]>
		<![CDATA[1001464.1002622.1000869.1000918.source=NVS]]>
		<![CDATA[1001464.1000851.1000869.1000918.vtc=true]]>
		<![CDATA[1001464.1002622.1000865.1000987.alacarte=true]]>
		<![CDATA[1001464.1002622.1000859.1000877.specialexteriorcolorflag=false]]>
		<![CDATA[1001464.1002622.1000859.1000876.specialinteriorcolorflag=false]]>
		<![CDATA[1001464.1002622.1000857.1000959.group=Interior]]>
		<![CDATA[1001464.1000851.1000869.1000913.alacarte=true]]>
		<![CDATA[1001464.1002622.1000857.1000948.msrp=100]]>
		<![CDATA[1001464.1002622.1000859.1000876.derived=false]]>
		<![CDATA[1001464.1002622.1000869.1000914.title=All-Weather Floor Mat and  Cargo Mat]]>
		<![CDATA[1001464.1000851.1000869.1000917.description=The all-weather cargo mat helps protect the cargo area from premature wear and tear.<br>&bull;Made of tough, easy-to-clean material and featuring a sculpted Venza logo<br>&bull;Skid-resistant surface helps keep items in place&bull;Designed for an exact fit to your Venza’s cargo area<br><br><i>Cargo and load capacity are limited by weight and distribution. </i>]]>
		<![CDATA[1001464.1000851.1000857.1000958.msrp=100.00]]>
		<![CDATA[1001464.1002622.1000857.1000960.derived=false]]>
		<![CDATA[1001464.1002622.1000857.1000950.package=false]]>
		<![CDATA[1001464.1002622.1000859.1000875.msrp=100]]>
		<![CDATA[1001464.1002622.1000865.1000981.msrp=105]]>
		<![CDATA[1001464.1000851.1000869.1000915.alacarte=true]]>
		<![CDATA[1001464.1000851.1000856.1000937.title=All Weather Cargo Mat [installed_msrp]]]>
		<![CDATA[1001464.1002622.1000857.1000949.group=Interior]]>
		<![CDATA[1001464.1002622.1000857.1000954.option=false]]>
		<![CDATA[1001464.1002622.1000859.1000878.alacarte=true]]>
		<![CDATA[1001464.1000851.1000857.alacarte=true]]>
		<![CDATA[1001464.1002622.1000865.1000980.marketingeffectivedate=]]>
		<![CDATA[1001464.1000851.1000865.1000982.msrp=105.00]]>
		<![CDATA[1001464.1000851.1000869.1000914.source=NVS]]>
		<![CDATA[1001464.1000851.1000869.1000918.derived=false]]>
		<![CDATA[1001464.1002622.1000869.1000917.source=NVS]]>
		<![CDATA[1001464.1000851.1000859.1000878.derived=false]]>
		<![CDATA[1001464.1002622.1000857.1000951.description=Available in black, gray or almond, the cargo liner helps you carry all types of items and protect your cargo area carpeting.<br>• Tough, easy-to-clean material is embossed with a Toyota logo and features a skid-resistant surface that helps keep items in place<br>• The cargo liner attaches to third-row seatbacks, allowing seats to be adjusted independently]]>
		<![CDATA[1001464.1000851.1000869.1000913.group=Interior]]>
		<![CDATA[1001464.1002622.1000857.1000954.derived=false]]>
		<![CDATA[1001464.1000851.1000857.1000951.msrp=100.00]]>
		<![CDATA[1001464.1002622.1000869.1000912.specialinteriorcolorflag=false]]>
		<![CDATA[1001464.1000851.1000858.videokey=]]>
		<![CDATA[1001464.1002622.1000857.1000956.title=Cargo Liner  [installed_msrp]]]>
		<![CDATA[1001464.1000851.1000869.1000912.group=Interior]]>
		<![CDATA[1001464.1002622.1000859.1000877.group=Interior]]>
		<![CDATA[1001464.1002622.1000859.1000875.videokey=]]>
		<![CDATA[1001464.1002622.1000857.1000948.secondaryfeatures=]]>
		<![CDATA[1001464.1000851.1000857.1000956.description=Tough and flexible, the cargo liner enables you to carry all types of items while helping protect your cargo area carpeting<br>&bull; Made of tough, easy-to-clean material and features a Toyota logo<br>&bull; Skid-resistant surface helps keep items in place<br>&bull; Attaches to third row seatbacks allowing seats to be adjusted independently<br>&bull; Available in black, gray and almond]]>
		<![CDATA[1001464.1002622.1000869.1000919.vtc=false]]>
		<![CDATA[1001464.1002622.1000865.1000984.description=The tough, flexible all- weather cargo mat allows you to carry a wide variety of items and helps protect your cargo area carpeting.<br>• Made of durable, easy-to-clean material embossed with a Sequoia logo<br>• Skid-resistant surface helps secure items in place]]>
		<![CDATA[1001464.1000851.1000856.1000937.msrp=100.00]]>
		<![CDATA[1001464.1002622.1000857.1000954.alacarte=true]]>
		<![CDATA[1001464.1002622.1000869.1000914.package=false]]>
		<![CDATA[1001464.1002622.1000865.1000986.description=The tough, flexible all- weather cargo mat allows you to carry a wide variety of items and helps protect your cargo area carpeting.<br>• Made of durable, easy-to-clean material embossed with a Sequoia logo<br>• Skid-resistant surface helps secure items in place]]>
		<![CDATA[1001464.1000851.1000856.1000937.viewpointkey=]]>
		<![CDATA[1001464.1002622.1000869.1000912.msrp=100]]>
		<![CDATA[1001464.1000851.1000859.1000876.source=NVS]]>
		<![CDATA[1001464.1002622.1000859.1000877.title=All-Weather Cargo Mat  [installed_msrp]]]>
		<![CDATA[1001464.1000851.1000865.1000987.title=All-Weather Cargo Mat [installed_msrp]]]>
		<![CDATA[1001464.1000851.1000865.1000983.title=All Weather Cargo Mat]]>
		<![CDATA[1001464.1002622.1000857.1000954.package=false]]>
		<![CDATA[1001464.1002622.1000857.1000955.option=false]]>
		<![CDATA[1001464.1002622.1000869.1000918.title=All-Weather Floor Mat and  Cargo Mat]]>
		<![CDATA[1001464.1002622.1000857.1000960.package=false]]>
		<![CDATA[1001464.1000851.1000857.1000953.description=Tough and flexible, the cargo liner enables you to carry all types of items while helping protect your cargo area carpeting<br>&bull; Made of tough, easy-to-clean material and features a Toyota logo<br>&bull; Skid-resistant surface helps keep items in place<br>&bull; Attaches to third row seatbacks allowing seats to be adjusted independently<br>&bull; Available in black, gray and almond]]>
		<![CDATA[1001464.1002622.1000857.1000952.option=false]]>
		<![CDATA[1001464.type=PIO]]>
		<![CDATA[1001464.1002622.1000857.1000959.derived=false]]>
		<![CDATA[1001464.1002622.1000857.1000956.description=Available in black, gray or almond, the cargo liner helps you carry all types of items and protect your cargo area carpeting.<br>• Tough, easy-to-clean material is embossed with a Toyota logo and features a skid-resistant surface that helps keep items in place<br>• The cargo liner attaches to third-row seatbacks, allowing seats to be adjusted independently]]>
		<![CDATA[1001464.1002622.1000857.1000948.marketingeffectivedate=]]>
		<![CDATA[1001464.1002622.1000869.1000918.derived=false]]>
		<![CDATA[1001464.1002622.1000857.1000958.title=Cargo Liner  [installed_msrp]]]>
		<![CDATA[1001464.1000851.1000869.1000921.title=All Weather Mat - Cargo Mat]]>
		<![CDATA[1001464.1000851.1000869.1000916.description=The all-weather cargo mat helps protect the cargo area from premature wear and tear.<br>&bull;Made of tough, easy-to-clean material and featuring a sculpted Venza logo<br>&bull;Skid-resistant surface helps keep items in place&bull;Designed for an exact fit to your Venza’s cargo area<br><br><i>Cargo and load capacity are limited by weight and distribution. </i>]]>
		<![CDATA[1001464.1002622.1000865.1000981.package=false]]>
		<![CDATA[1001464.1000851.1000856.vtc=true]]>
		<![CDATA[1001464.1002622.1000859.1000875.viewpointkey=]]>
		<![CDATA[1001464.1000851.1000859.description=Tough and flexible, the cargo mat helps protect your cargo area carpeting when transporting all types of items. <br>&bull; Made of tough, easy-to-clean material<br>&bull; Skid-resistant surface helps keep items in place<br>&bull; Designed for an exact fit to the cargo area<br>&bull; Features an embossed Prius logo]]>
		<![CDATA[1001464.1000851.1000869.1000914.alacarte=true]]>
		<![CDATA[1001464.1000851.1000869.1000916.derived=false]]>
		<![CDATA[1001464.1002622.1000869.1000918.msrp=100.00]]>
		<![CDATA[1001464.1000851.1000856.1000938.option=false]]>
		<![CDATA[1001464.1002622.1000859.1000875.title=All-Weather Cargo Mat  [installed_msrp]]]>
		<![CDATA[1001464.1000851.1000864.group=Interior]]>
		<![CDATA[1001464.1000851.1000869.1000921.group=Interior]]>
		<![CDATA[1001464.1002622.1000869.1000918.alacarte=true]]>
		<![CDATA[1001464.1000851.1000865.1000988.derived=false]]>
		<![CDATA[1001464.1002622.1000859.1000877.package=false]]>
		<![CDATA[1001464.1000851.1000857.1000960.title=Cargo Liner]]>
		<![CDATA[1001464.1002622.1000865.1000983.title=All Weather Cargo Mat [installed_msrp]]]>
		<![CDATA[1001464.1000851.1000858.1000947.pnglayeringinclusionkey=]]>
		<![CDATA[1001464.1000851.1000869.1000914.description=The all-weather cargo mat helps protect the cargo area from premature wear and tear.<br>&bull;Made of tough, easy-to-clean material and featuring a sculpted Venza logo<br>&bull;Skid-resistant surface helps keep items in place&bull;Designed for an exact fit to your Venza’s cargo area<br><br><i>Cargo and load capacity are limited by weight and distribution. </i>]]>
		<![CDATA[1001464.1000851.1000869.1000915.group=Interior]]>
		<![CDATA[1001464.1002622.1000857.1000956.derived=false]]>
		<![CDATA[1001464.1002622.1000857.1000958.specialinteriorcolorflag=false]]>
		<![CDATA[1001464.1000851.1000865.1000980.msrp=105.00]]>
		<![CDATA[1001464.1000851.1000858.secondaryfeatures=]]>
		<![CDATA[1001464.1002622.1000865.1000987.title=All Weather Cargo Mat [installed_msrp]]]>
		<![CDATA[1001464.1000851.1000858.description=Tough and flexible, the all-weather cargo mat is uniquely designed to fit, enabling you to carry all types of cargo without worrying about soils and stains. It features a skid-resistant surface to help contain spills.<br /><br /><em>Cargo and load capacity limited by weight and distribution.</em>]]>
		<![CDATA[1001464.1002622.1000869.1000919.derived=false]]>
		<![CDATA[1001464.1000851.1000857.1000950.msrp=100.00]]>
		<![CDATA[1001464.1002622.1000857.1000959.specialinteriorcolorflag=false]]>
		<![CDATA[1001464.1000851.1000869.1000921.source=NVS]]>
		<![CDATA[1001464.1000851.1000869.1000916.group=Interior]]>
		<![CDATA[1001464.1002622.1000859.1000876.option=false]]>
		<![CDATA[1001464.1002622.1000865.1000986.derived=true]]>
		<![CDATA[1001464.1002622.1000859.1000878.msrp=100]]>
		<![CDATA[1001464.1000851.1000865.1000982.derived=false]]>
		<![CDATA[1001464.1000851.1000869.1000916.title=All Weather Mat - Cargo Mat]]>
		<![CDATA[1001464.1000851.1000857.1000951.derived=false]]>
		<![CDATA[1001464.1000851.1000869.1000921.derived=false]]>
		<![CDATA[1001464.1000851.1000856.1000938.description=An essential accessory to accompany you on your adventures, this custom-fitted cargo tray helps keep your cargo area clean and dry:<br />•Cut to an exact fit of your FJ’s cargo area<br />•Multidimensional surface and perimeter lip help contain dirt, debris and liquids<br />•Molded FJ logo adds a touch of customization<br /><br /><em>Cargo load and capacity limited by weight and distribution.</em>ion.]]>
		<![CDATA[1001464.1002622.1000857.1000951.alacarte=true]]>
		<![CDATA[1001464.1002622.1000857.1000955.title=Cargo Liner  [installed_msrp]]]>
		<![CDATA[1001464.1000851.1000857.1000960.derived=false]]>
		<![CDATA[1001464.1002622.1000857.1000959.alacarte=true]]>
		<![CDATA[1001464.1000851.1000869.1000915.vtc=true]]>
		<![CDATA[1001464.1000851.1000857.1000957.title=Cargo Liner]]>
		<![CDATA[1001464.1000851.1000856.1000938.viewpointkey=]]>
		<![CDATA[1001464.1002622.1000865.1000982.option=false]]>
		<![CDATA[1001464.1002622.1000869.1000917.title=All-Weather Floor Mat and  Cargo Mat]]>
		<![CDATA[1001464.1002622.1000869.1000912.source=NVS]]>
		<![CDATA[1001464.1002622.1000859.1000878.option=false]]>
		<![CDATA[1001464.1002622.1000869.1000917.package=false]]>
		<![CDATA[1001464.1002622.1000857.1000951.group=Interior]]>
		<![CDATA[1001464.1002622.1000865.1000988.msrp=105]]>
		<![CDATA[1001464.1002622.1000857.1000950.source=NVS]]>
		<![CDATA[1001464.1000851.1000869.1000912.vtc=true]]>
		<![CDATA[1001464.1002622.1000858.1000947.viewpointkey=]]>
		<![CDATA[1001464.1002622.1000865.1000986.title=All Weather Cargo Mat [installed_msrp]]]>
		<![CDATA[1001464.1002622.1000859.1000875.alacarte=true]]>
		<![CDATA[1001464.1000851.1000856.1000938.specialinteriorcolorflag=false]]>
		<![CDATA[1001464.1002622.1000865.1000982.description=The tough, flexible all- weather cargo mat allows you to carry a wide variety of items and helps protect your cargo area carpeting.<br>• Made of durable, easy-to-clean material embossed with a Sequoia logo<br>• Skid-resistant surface helps secure items in place]]>
		<![CDATA[1001464.1002622.1000865.1000985.specialinteriorcolorflag=false]]>
		<![CDATA[1001464.1002622.1000857.1000950.group=Interior]]>
		<![CDATA[1001464.1002622.1000865.1000985.description=The tough, flexible all- weather cargo mat allows you to carry a wide variety of items and helps protect your cargo area carpeting.<br>• Made of durable, easy-to-clean material embossed with a Sequoia logo<br>• Skid-resistant surface helps secure items in place]]>
		<![CDATA[1001464.1002622.1000859.1000875.package=false]]>
		<![CDATA[1001464.1002622.1000869.1000916.derived=false]]>
		<![CDATA[1001464.1002622.1000869.1000912.keyfeatures=]]>
		<![CDATA[1001464.1000851.1000857.1000953.source=NVS]]>
		<![CDATA[1001464.1002622.1000865.1000987.description=The tough, flexible all- weather cargo mat allows you to carry a wide variety of items and helps protect your cargo area carpeting.<br>• Made of durable, easy-to-clean material embossed with a Sequoia logo<br>• Skid-resistant surface helps secure items in place]]>
		<![CDATA[1001464.1002622.1000869.1000921.vtc=false]]>
		<![CDATA[1001464.1002622.1000859.1003292.specialinteriorcolorflag=false]]>
		<![CDATA[1001464.1002622.1000865.1000984.derived=true]]>
		<![CDATA[1001464.1000851.1000859.1000876.description=Tough and flexible, the cargo mat helps protect your cargo area carpeting when transporting all types of items. <br>&bull; Made of tough, easy-to-clean material<br>&bull; Skid-resistant surface helps keep items in place<br>&bull; Designed for an exact fit to the cargo area<br>&bull; Features an embossed Prius logo]]>
		<![CDATA[1001464.1000851.1000857.description=Tough and flexible, the cargo liner enables you to carry all types of items while helping protect your cargo area carpeting<br>&bull; Made of tough, easy-to-clean material and features a Toyota logo<br>&bull; Skid-resistant surface helps keep items in place<br>&bull; Attaches to third row seatbacks allowing seats to be adjusted independently<br>&bull; Available in black, gray and almond]]>
		<![CDATA[1001464.1002622.1000865.1000985.group=Interior]]>
		<![CDATA[1001464.1000851.1000859.1000877.derived=false]]>
		<![CDATA[1001464.1000851.1000859.1000878.source=NVS]]>
		<![CDATA[1001464.1002622.1000857.1000948.group=Interior]]>
		<![CDATA[1001464.1002622.1000857.1000954.source=NVS]]>
		<![CDATA[1001464.1000851.1000869.1000920.derived=false]]>
		<![CDATA[1001464.1000851.1000869.1000915.derived=false]]>
		<![CDATA[1001464.1002622.1000858.1000947.group=Interior]]>
		<![CDATA[1001464.1000851.1000856.1000936.secondaryfeatures=]]>
		<![CDATA[1001464.1000851.1000857.1000952.title=Cargo Liner]]>
		<![CDATA[1001464.1002622.1000869.1000917.derived=false]]>
		<![CDATA[1001464.1000851.1000857.1000957.msrp=100.00]]>
		<![CDATA[1001464.1002622.1000857.1000955.specialinteriorcolorflag=false]]>
		<![CDATA[1001464.1002622.1000857.1000950.option=false]]>
		<![CDATA[1001464.1002622.1000857.1000951.specialexteriorcolorflag=false]]>
		<![CDATA[1001464.1002622.1000865.1000986.option=false]]>
		<![CDATA[1001464.1000851.1000856.1000937.keyfeatures=]]>
		<![CDATA[1001464.1002622.1000857.1000949.msrp=100]]>
		<![CDATA[1001464.1000851.1000856.title=All-Weather Cargo Mat [installed_msrp]]]>
		<![CDATA[1001464.1002622.1000857.1000958.package=false]]>
		<![CDATA[1001464.1002622.1000869.1000921.source=NVS]]>
		<![CDATA[1001464.1000851.1000869.1000920.description=The all-weather cargo mat helps protect the cargo area from premature wear and tear.<br>&bull;Made of tough, easy-to-clean material and featuring a sculpted Venza logo<br>&bull;Skid-resistant surface helps keep items in place&bull;Designed for an exact fit to your Venza’s cargo area<br><br><i>Cargo and load capacity are limited by weight and distribution. </i>]]>
		<![CDATA[1001464.1000851.1000865.1000988.msrp=105.00]]>
		<![CDATA[1001464.1000851.1000859.1000878.msrp=100.00]]>
		<![CDATA[1001464.1002622.1000857.1000959.msrp=100]]>
		<![CDATA[1001464.1002622.1000869.1000912.specialexteriorcolorflag=false]]>
		<![CDATA[1001464.1000851.1000856.1000937.specialinteriorcolorflag=false]]>
		<![CDATA[1001464.1002622.1000865.1000988.derived=true]]>
		<![CDATA[1001464.1000851.1000857.1000958.title=Cargo Liner]]>
		<![CDATA[1001464.1002622.1000857.1000952.source=NVS]]>
		<![CDATA[1001464.1002622.1000857.1000948.option=false]]>
		<![CDATA[1001464.1002622.1000869.1000921.derived=false]]>
		<![CDATA[1001464.1002622.1000858.1000947.specialexteriorcolorflag=false]]>
		<![CDATA[1001464.1000851.1000859.1000875.description=Tough and flexible, the cargo mat helps protect your cargo area carpeting when transporting all types of items. <br>&bull; Made of tough, easy-to-clean material<br>&bull; Skid-resistant surface helps keep items in place<br>&bull; Designed for an exact fit to the cargo area<br>&bull; Features an embossed Prius logo]]>
		<![CDATA[1001464.1000851.1000865.description=The all-weather cargo mat helps protect the cargo area from premature wear and tear.<br>&bull; Made of tough, easy-to-clean material featuring an embossed Sequoia logo<br>&bull; Skid-resistant surface helps keep items in place<br>&bull; Designed for an exact fit to your Sequoia’s cargo area<br><br><i>Cargo and load capacity are limited by weight and distribution.</i>]]>
		<![CDATA[1001464.1000851.1000869.1000919.title=All Weather Mat - Cargo Mat]]>
		<![CDATA[1001464.1002622.1000869.1000917.vtc=false]]>
		<![CDATA[1001464.1002622.1000859.1000876.source=NVS]]>
		<![CDATA[1001464.1000851.1000857.1000954.title=Cargo Liner]]>
		<![CDATA[1001464.1000851.1000857.1000950.derived=false]]>
		<![CDATA[1001464.1002622.1000865.1000981.alacarte=true]]>
		<![CDATA[1001464.1000851.1000869.1000919.group=Interior]]>
		<![CDATA[1001464.1000851.1000869.1000918.description=The all-weather cargo mat helps protect the cargo area from premature wear and tear.<br>&bull;Made of tough, easy-to-clean material and featuring a sculpted Venza logo<br>&bull;Skid-resistant surface helps keep items in place&bull;Designed for an exact fit to your Venza’s cargo area<br><br><i>Cargo and load capacity are limited by weight and distribution. </i>]]>
		<![CDATA[1001464.1002622.1000857.1000956.package=false]]>
		<![CDATA[1001464.1002622.1000859.1000877.source=NVS]]>
		<![CDATA[1001464.1000851.1000857.1000952.source=NVS]]>
		<![CDATA[1001464.1000851.1000869.1000914.group=Interior]]>
		<![CDATA[1001464.1002622.1000857.1000948.derived=false]]>
		<![CDATA[1001464.1000851.1000857.1000954.description=Tough and flexible, the cargo liner enables you to carry all types of items while helping protect your cargo area carpeting<br>&bull; Made of tough, easy-to-clean material and features a Toyota logo<br>&bull; Skid-resistant surface helps keep items in place<br>&bull; Attaches to third row seatbacks allowing seats to be adjusted independently<br>&bull; Available in black, gray and almond]]>
		<![CDATA[1001464.1000851.1000865.1000981.source=NVS]]>
		<![CDATA[1001464.1000851.1000857.1000954.derived=false]]>
		<![CDATA[1001464.1000851.1000869.1000918.source=NVS]]>
		<![CDATA[1001464.1002622.1000865.1000980.alacarte=true]]>
		<![CDATA[1001464.1002622.1000857.1000950.msrp=100]]>
		<![CDATA[1001464.1002622.1000859.1003292.derived=false]]>
		<![CDATA[1001464.1002622.1000865.1000983.option=false]]>
		<![CDATA[1001464.1000851.1000859.1000875.source=NVS]]>
		<![CDATA[1001464.1000851.1000858.alacarte=true]]>
		<![CDATA[1001464.1000851.1000856.1000936.specialexteriorcolorflag=false]]>
		<![CDATA[1001464.1002622.1000857.1000956.msrp=100]]>
		<![CDATA[1001464.1000851.1000869.1000921.msrp=100.00]]>
		<![CDATA[1001464.1002622.1000857.1000950.specialinteriorcolorflag=false]]>
		<![CDATA[1001464.1002622.1000869.1000916.vtc=false]]>
		<![CDATA[1001464.1000851.1000869.1000918.alacarte=true]]>
		<![CDATA[1001464.1002622.1000865.1000987.specialexteriorcolorflag=false]]>
		<![CDATA[1001464.1002622.1000857.1000959.source=NVS]]>
		<![CDATA[1001464.1000851.1000859.1000875.title=All Weather Cargo Mat]]>
		<![CDATA[1001464.1002622.1000865.1000988.specialinteriorcolorflag=false]]>
		<![CDATA[1001464.1000851.1000869.1000919.derived=false]]>
		<![CDATA[1001464.1002622.1000865.1000982.alacarte=true]]>
		<![CDATA[1001464.1000851.1000859.1000877.msrp=100.00]]>
		<![CDATA[1001464.1000851.1000865.msrp=105]]>
		<![CDATA[1001464.1002622.1000857.1000957.package=false]]>
		<![CDATA[1001464.1000851.1000857.1000953.msrp=100.00]]>
		<![CDATA[1001464.1002622.1000869.1000912.pnglayeringinclusionkey=]]>
		<![CDATA[1001464.1002622.1000865.1000984.option=false]]>
		<![CDATA[1001464.1000851.1000857.1000956.derived=false]]>
	</resource>
