	<resource id='1001383' type='grade'>
		<![CDATA[1001383.1000851.1000857.1000959.hotspot=260,135,C]]>
		<![CDATA[1001383.1002622.1000853.1000924.hotspot=]]>
		<![CDATA[1001383.1000851.1000857.1000959.availablecopy=Rear-seat Blu-ray Disc<sup>&trade;</sup> entertainment system, Driver Technology Package: Safety Connect<sup>&reg;</sup>, [safety_connect] Pre-Collision System [pre_collision]  with Dynamic Radar Cruise Control, [drcc] Lane Departure Alert [ldw] with Automatic High Beam [auto_highbeam] headlights]]>
		<![CDATA[1001383.1000851.1000857.1000959.mpg=]]>
		<![CDATA[1001383.title=Hybrid Limited]]>
		<![CDATA[1001383.1000851.1000853.1000924.derived=false]]>
		<![CDATA[1001383.1002622.1000853.1000924.keyword=]]>
		<![CDATA[1001383.1002622.1000853.1000924.derived=false]]>
		<![CDATA[1001383.1000851.1000857.1000959.description=Hybrid Limited]]>
		<![CDATA[1001383.1000851.1000853.1000924.availablecopy=Dynamic Radar Cruise Control (DRCC), [drcc] Pre-Collision System (PCS), [pre_collision] Qi wireless charging [qi_wireless] capability for eBin&trade; storage tray]]>
		<![CDATA[1001383.source=true]]>
		<![CDATA[1001383.1000851.1000857.1000960.keyword=Efficiency and luxury in an adventurous package.<br>&bull; 3.5-liter V6 with Hybrid Synergy Drive<sup>&reg;</sup><br>&bull; 280 net hp; Electronic AWD-i]]>
		<![CDATA[1001383.vtc=true]]>
		<![CDATA[1001383.1000851.1000853.1000924.keyword=]]>
		<![CDATA[1001383.1000851.1000853.1000924.mpg=]]>
		<![CDATA[1001383.1000851.1000857.1000959.iconname=]]>
		<![CDATA[1001383.1000851.1000857.1000959.derived=false]]>
		<![CDATA[1001383.1002622.1000857.1000960.derived=false]]>
		<![CDATA[1001383.1002622.1000857.1000960.mpg=]]>
		<![CDATA[1001383.1002622.1000857.1000959.derived=false]]>
		<![CDATA[1001383.1002622.1000857.1000960.description=]]>
		<![CDATA[1001383.1000851.1000857.1000959.copyblock=A powerful and efficient performer.<br>&bull; 3.5-liter V6 with Hybrid Synergy Drive&reg;<br>&bull; 280 net hp; Electronic AWD-i]]>
		<![CDATA[1001383.1002622.1000857.1000959.hotspot=260,135,C]]>
		<![CDATA[1001383.1002622.1000857.1000959.iconname=]]>
		<![CDATA[1001383.1000851.1000853.1000924.iconname=]]>
		<![CDATA[1001383.1002622.1000853.1000924.description=]]>
		<![CDATA[1001383.1002622.1000857.1000960.keyword=]]>
		<![CDATA[1001383.1002622.1000857.1000959.description=]]>
		<![CDATA[1001383.1002622.1000857.1000959.mpg=]]>
		<![CDATA[1001383.1002622.1000857.1000960.copyblock=Efficiency and luxury in an adventurous package.<br>&bull; 3.5-liter V6 with Hybrid Synergy Drive<sup>&reg;</sup><br>&bull; 280 net hp; Electronic AWD-i]]>
		<![CDATA[1001383.1000851.1000853.1000924.hotspot=290,131,R]]>
		<![CDATA[1001383.1002622.1000853.1000924.mpg=]]>
		<![CDATA[1001383.1002622.1000857.1000959.keyword=]]>
		<![CDATA[1001383.1002622.1000853.1000924.availablecopy=Dynamic Radar Cruise Control (DRCC), [drcc] Pre-Collision System (PCS), [pre_collision] Qi wireless charging [qi_wireless] capability for eBin<sup>&trade;</sup> storage tray, Auto High Beam (AHB) [auto_highbeam]]]>
		<![CDATA[1001383.1002622.1000857.1000959.copyblock=A powerful and efficient performer.<br>&bull; 3.5-liter V6 with Hybrid Synergy Drive<sup>&reg;</sup><br>&bull; 280 net hp; Electronic AWD-i]]>
		<![CDATA[1001383.1002622.1000857.1000960.hotspot=260,135,C]]>
		<![CDATA[1001383.1002622.1000853.1000924.iconname=]]>
		<![CDATA[1001383.1002622.1000857.1000959.availablecopy=Rear-seat Blu-ray Disc<sup>&trade;</sup> entertainment system, Driver Technology Package: Safety Connect<sup>&reg;</sup>, [safety_connect] Pre-Collision System [pre_collision]  with Dynamic Radar Cruise Control, [drcc] Lane Departure Alert [ldw] with Automatic High Beam [auto_highbeam] headlights]]>
		<![CDATA[1001383.1000851.1000853.1000924.copyblock=Where art and technology converge.<br>&bull; 2.5L 4-Cylinder Hybrid ECO and Sport Modes<br>&bull; Electronically controlled Continuously Variable Transmission (ECVT)]]>
		<![CDATA[1001383.1002622.1000853.1000924.copyblock=Redefine the driving experience.<br>&bull; 2.5L 4-Cylinder Hybrid ECVT<br>&bull; EV, [ev_mode] ECO and Sport Modes]]>
		<![CDATA[1001383.1000851.1000857.1000959.keyword=A powerful and efficient performer.<br>&bull; 3.5-liter V6 with Hybrid Synergy Drive<sup>&reg;</sup><br>&bull; 280 net hp; Electronic AWD-i]]>
		<![CDATA[1001383.1002622.1000857.1000960.title=Hybrid Limited]]>
		<![CDATA[1001383.1000851.1000857.1000960.title=Hybrid Limited Platinum]]>
		<![CDATA[1001383.1002622.1000857.1000960.availablecopy=]]>
		<![CDATA[1001383.1002622.1000857.1000960.iconname=]]>
		<![CDATA[1001383.1000851.1000853.1000924.description=]]>
	</resource>
