{"views":[{"name":"Exterior","layers":[{"name":"03_Paint","children":[{"GRD_L":[{"XCOL_01F7":[[3,"09eef1d"],[2,"2172fa2"],[4,"f4a0643"],[1,"ecc2dd7"]]},{"XCOL_04V8":[[4,"b969051"],[2,"f074e23"],[1,"d9441ce"],[3,"6412f97"]]},{"XCOL_06W3":[[3,"c7dfb8c"],[1,"ef54fa1"],[2,"d9d9e64"],[4,"d9a23b8"]]},{"XCOL_0070":[[2,"694a7a5"],[3,"4affb05"],[1,"01e8162"],[4,"323c91b"]]},{"XCOL_03R3":[[4,"0bac814"],[2,"8eb757a"],[3,"43305f2"],[1,"d5cdda5"]]},{"XCOL_0040":[[2,"d948b87"],[1,"7095514"],[3,"579455f"],[4,"255991b"]]},{"XCOL_0209":[[2,"575fed5"],[1,"a160a5e"],[4,"81c80d6"],[3,"9732e30"]]},{"XCOL_01F9":[[2,"5a2bad0"],[4,"734b6bc"],[3,"d0078f3"],[1,"5fef755"]]}]},{"GRD_S":[{"XCOL_08W7":[[4,"f48ddb4"],[2,"1c91e88"],[3,"9893a41"],[1,"cc384af"]]},{"XCOL_0040":[[1,"499e167"],[4,"27166d1"],[2,"ac5db1e"],[3,"ae2c061"]]},{"XCOL_0209":[[4,"7b28a10"],[1,"d82c882"],[3,"4edfa9b"],[2,"1314dcb"]]},{"XCOL_03R3":[[4,"572f017"],[2,"d774ef9"],[3,"9d4acf2"],[1,"29128d1"]]},{"XCOL_01F7":[[2,"40904b2"],[1,"e398588"],[3,"426d600"],[4,"c6968a7"]]},{"XCOL_01F9":[[4,"a46a301"],[2,"975eac7"],[3,"a3e7a8a"],[1,"a6fc716"]]}]},{"GRD_eco":[{"XCOL_01F9":[[1,"88f449d"],[4,"073bfca"],[2,"612f44a"],[3,"6d57a98"]]},{"XCOL_01F7":[[3,"b7b3289"],[4,"0723119"],[1,"f666103"],[2,"e63ae21"]]},{"XCOL_03R3":[[3,"e45e3ba"],[1,"931d6cc"],[2,"917183a"],[4,"43a65b9"]]},{"XCOL_04V8":[[1,"c0b422a"],[3,"205ffe4"],[2,"46a3876"],[4,"e887808"]]},{"XCOL_0209":[[3,"c80ec21"],[2,"2bd4b95"],[4,"0d26d3c"],[1,"8466611"]]},{"XCOL_0070":[[1,"d8adb33"],[3,"3b2fd92"],[4,"d37f837"],[2,"b6fa5cb"]]},{"XCOL_06W3":[[3,"b33fa40"],[2,"35ef1b3"],[4,"e489344"],[1,"580d3b9"]]}]},{"GRD_LE":[{"XCOL_0209":[[3,"184d97a"],[2,"1298933"],[4,"25a5301"],[1,"77aee7c"]]},{"XCOL_01F9":[[2,"3c02f0f"],[1,"1a14f07"],[4,"7b68b5d"],[3,"6811462"]]},{"XCOL_06W3":[[3,"c9cee48"],[2,"62bbe0f"],[1,"5408e5d"],[4,"3589202"]]},{"XCOL_04V8":[[3,"99ef7f3"],[4,"b6b0fbf"],[2,"0537bfc"],[1,"294a205"]]},{"XCOL_01F7":[[3,"2152764"],[2,"d227dbb"],[4,"b77be4a"],[1,"b97eae1"]]},{"XCOL_0070":[[2,"62af914"],[3,"789b573"],[1,"11e2ecb"],[4,"30d803e"]]},{"XCOL_03R3":[[4,"329f369"],[2,"df0b5c7"],[3,"9663367"],[1,"5b6dbcd"]]},{"XCOL_0040":[[2,"fb00fcb"],[1,"d7ab734"],[4,"9ce6903"],[3,"2250feb"]]}]}],"lift":false},{"name":"05_Door_Handle","children":[{"ABF_Smartkey":[{"XCOL_08W7":[[1,"62a0b63"],[2,"5185888"],[4,"bc540e5"],[3,"86051b9"]]},{"XCOL_0070":[[1,"4f80f8b"],[2,"2ffb606"],[3,"e8c2492"],[4,"996d7b3"]]},{"XCOL_01F7":[[4,"4422adb"],[3,"0850107"],[2,"1414670"],[1,"4b38b88"]]},{"XCOL_01F9":[[1,"a35568c"],[3,"50340d3"],[2,"5edaf59"],[4,"f9f4c37"]]},{"XCOL_03R3":[[1,"c177f77"],[3,"29bc4bf"],[4,"c542a9b"],[2,"e2b4068"]]},{"XCOL_04V8":[[1,"41ab21c"],[3,"f806f51"],[4,"779929f"],[2,"3e3fdb1"]]},{"XCOL_0040":[[3,"c83abdf"],[2,"37b4c2c"],[1,"e0f529e"],[4,"0e89a0e"]]},{"XCOL_0209":[[2,"3f4f6c9"],[4,"43f3f20"],[1,"b30440c"],[3,"9de506d"]]},{"XCOL_06W3":[[1,"5671a2b"],[3,"40207a1"],[2,"9c5043f"],[4,"4ce2f20"]]}]},{"XCOL_0040":[[2,"f99b242"],[4,"7972cf4"],[1,"e3c2738"],[3,"7c0069f"]]},{"XCOL_0070":[[4,"2950c9b"],[2,"8f15c92"],[3,"c0cf3b7"],[1,"7d71896"]]},{"XCOL_01F7":[[1,"5f21406"],[4,"93cc248"],[3,"5af232a"],[2,"60b50ad"]]},{"XCOL_01F9":[[4,"45ffc5f"],[3,"b808868"],[1,"78378cf"],[2,"852aa70"]]},{"XCOL_0209":[[2,"769ebac"],[4,"81b4be6"],[1,"9fe9419"],[3,"5c070ce"]]},{"XCOL_03R3":[[4,"677e458"],[1,"30043a0"],[3,"ffdaa44"],[2,"e39ae8b"]]},{"XCOL_04V8":[[4,"0f33240"],[1,"5e29abc"],[3,"c7ed198"],[2,"6fb7c36"]]},{"XCOL_06W3":[[2,"8f18eec"],[4,"45845a2"],[3,"d308607"],[1,"df20be1"]]},{"XCOL_08W7":[[4,"51a03d8"],[2,"0bcb294"],[1,"df93da8"],[3,"64e5cf2"]]}],"lift":false},{"name":"05_Fog_Lamps","children":[{"ABF_Foglights":[[1,"223f7a3"],[2,"df0ddb2"],[3,"ea137ba"],[4,"6fa1850"]]}],"lift":false},{"name":"03_Spoiler","children":[{"ABF_Spoiler":[{"XCOL_0040":[[3,"e758237"],[2,"5c09e4a"],[1,"ea137ba"],[4,"15872b4"]]},{"XCOL_0070":[[3,"8b7c1b6"],[2,"674da41"],[1,"ea137ba"],[4,"77970b5"]]},{"XCOL_01F7":[[1,"ea137ba"],[4,"e995034"],[2,"1ea0d2e"],[3,"b73643c"]]},{"XCOL_01F9":[[3,"067288a"],[2,"e268454"],[4,"291eb5f"],[1,"ea137ba"]]},{"XCOL_0209":[[1,"ea137ba"],[3,"c408d81"],[4,"3cdabf5"],[2,"f8b2054"]]},{"XCOL_03R3":[[2,"585ee02"],[3,"0faa067"],[1,"ea137ba"],[4,"77edb85"]]},{"XCOL_04V8":[[2,"e7dc266"],[3,"2019c56"],[4,"306b9fb"],[1,"ea137ba"]]},{"XCOL_06W3":[[4,"be00fe4"],[1,"ea137ba"],[2,"3978bda"],[3,"d5938cb"]]},{"XCOL_08W7":[[1,"ea137ba"],[2,"92e3613"],[4,"62ec917"],[3,"9e2d2d0"]]}]}],"lift":false},{"name":"05_Backup_Camera","children":[{"GRD_L":[[1,"ea137ba"],[2,"ea137ba"],[3,"ea137ba"],[4,"ea137ba"]]},[1,"ea137ba"],[2,"ea137ba"],[3,"7cf86c3"],[4,"ea137ba"]],"lift":false},{"name":"05_Badge","children":[{"GRD_S":[[4,"ea137ba"],[3,"27d4a42"],[2,"ea137ba"],[1,"ea137ba"]]},{"GRD_eco":[[4,"ea137ba"],[1,"ea137ba"],[2,"ea137ba"],[3,"c34504b"]]},{"GRD_LE":[[1,"ea137ba"],[3,"9df0a2d"],[2,"ea137ba"],[4,"ea137ba"]]}],"lift":false},{"name":"05_Turn_Signal","children":[{"GRD_S":[[1,"463319d"],[2,"8fad437"],[3,"ea137ba"],[4,"59a059e"]]}],"lift":false},{"name":"05_Grill","children":[{"GRD_S":[[1,"65608e3"],[2,"78c7433"],[4,"639b8cd"],[3,"ea137ba"]]},[1,"1202781"],[2,"745827d"],[3,"ea137ba"],[4,"a16fbec"]],"lift":false},{"name":"05_Beltline","children":[{"ABF_Chrome":[[1,"7a58c8e"],[3,"d0b29c5"],[2,"503eeb5"],[4,"8e7b429"]]},[1,"147bac8"],[2,"f62d1eb"],[3,"f5fbc44"],[4,"6e5b5a2"]],"lift":false},{"name":"05_Trunk_Lock","children":[{"ABF_Smartkey":[[1,"ea137ba"],[4,"ea137ba"],[2,"ea137ba"],[3,"ea137ba"]]},[1,"ea137ba"],[2,"ea137ba"],[3,"15ac4c2"],[4,"ea137ba"]],"lift":false},{"name":"01_Shadow","children":[[2,"a005bf9"],[3,"f9a290e"],[1,"5cb20d5"],[4,"d3421f5"]],"lift":false},{"name":"02_Standard","children":[{"GRD_eco":[[3,"aefb543"],[2,"e1c0d62"],[1,"9b1caab"],[4,"1d9717e"]]},{"GRD_L":[[1,"cb29ea1"],[4,"62699be"],[2,"f7cbe5b"],[3,"6d8cc9e"]]},{"GRD_S":[[2,"2be813d"],[4,"e614b19"],[3,"2d3d443"],[1,"712756b"]]},{"GRD_LE":[[4,"9813580"],[1,"001f268"],[3,"93130be"],[2,"7ac104d"]]}],"lift":false},{"name":"05_Mirrors","children":[{"ABF_Mirror":[[4,"ea137ba"],[2,"ea137ba"],[1,"ea137ba"],[3,"d6a5e53"]]}],"lift":false},{"name":"06_Wheels","children":[{"GRD_LE":[[1,"f3a6dac"],[2,"2575b6d"],[4,"ac59ae9"],[3,"3a80179"],{"MDL_1852":[[3,"64f68af"],[1,"d14e06d"],[2,"31e807f"],[4,"1b63ca6"]]}]},{"GRD_eco":[{"ABF_Alloy":[[1,"6bf8d7c"],[3,"4133999"],[4,"bec11d8"],[2,"4deb070"]]}]},{"GRD_S":[[4,"2a022a0"],[2,"b7ecd43"],[3,"0cc4986"],[1,"1cbf1e1"],{"MDL_1862":[[3,"31d1067"],[1,"247c4a9"],[4,"7140cf1"],[2,"d8a5ac6"]]}]},[1,"9b09631"],[2,"b09c330"],[3,"e5d3dba"],[4,"c49db36"]],"lift":false},{"name":"05_Audio","children":[{"ABF_Smartkey":[[1,"ea137ba"],[2,"83baf0a"],[3,"61971a3"],[4,"346b526"]]}],"lift":false},{"name":"05_Bumper","children":[{"GRD_S":[[2,"84adca4"],[3,"ea137ba"],[1,"a65a9f9"],[4,"bb6ffeb"]]},{"GRD_LE":[[1,"ce15bf5"],[3,"ea137ba"],[2,"ef226ef"],[4,"495ab28"]]},{"GRD_eco":[[4,"9562f5f"],[1,"64793ef"],[2,"999df83"],[3,"ea137ba"]]},{"GRD_L":[[2,"682821a"],[3,"ea137ba"],[4,"b8795ab"],[1,"29d6204"]]}],"lift":false},{"name":"05_Exhaust","children":[{"GRD_S":[[3,"a736d6f"],[4,"ea137ba"],[1,"ea137ba"],[2,"ea137ba"]]},[1,"ea137ba"],[2,"ea137ba"],[3,"8e3018c"],[4,"ea137ba"]],"lift":false},{"name":"05_Roof","children":[{"ABF_Moonroof":[[4,"9b6bd76"],[3,"ea137ba"],[1,"e95d742"],[2,"365293a"]]}],"lift":false}]},{"name":"Interior","layers":[{"name":"05_Trim","children":[{"GRD_S":[[2,"7ead33f"],[1,"6e67636"],[3,"7ead33f"],[4,"07068d5"]]},[1,"90481bd"],[2,"7ead33f"],[3,"7ead33f"],[4,"71ba41a"]],"lift":false},{"name":"02_Standard","children":[{"GRD_S":[[2,"d8be747"],[1,"58df2e4"],[3,"6727cd6"],[4,"4ca6ec9"]]},{"ICOL_FB01":[[2,"088edc1"],[1,"7be6bf6"],[3,"58e552c"],[4,"b46424a"]]},{"ICOL_FB41":[[1,"d4b4b4f"],[2,"fc69e75"],[3,"db6719d"],[4,"d01709d"]]},{"GRD_L":[[1,"2027bb7"],[3,"7aa3ddc"],[2,"c173ec6"],[4,"caa257e"]]},[1,"d84b2f6"],[2,"10b4a3c"],[3,"b32f1f4"],[4,"a400c86"]],"lift":false},{"name":"05_PaddleShifter","children":[{"GRD_S":[{"TRAN_CVT":[[1,"cc95ff3"],[2,"7ead33f"],[3,"7ead33f"],[4,"755ae0a"]]}]},[1,"5082567"],[2,"7ead33f"],[3,"7ead33f"],[4,"bc2b8e0"]],"lift":false},{"name":"05_Gauges","children":[{"GRD_S":[[1,"e62b7e7"],[4,"b256451"],[2,"7ead33f"],[3,"7ead33f"]]},[1,"c63ddef"],[2,"7ead33f"],[3,"7ead33f"],[4,"4f9f1ca"]],"lift":false},{"name":"05_CruiseControl","children":[{"GRD_L":[[2,"7ead33f"],[3,"7ead33f"],[1,"7ead33f"],[4,"703efda"]]},[1,"97bbbdb"],[2,"7ead33f"],[3,"7ead33f"],[4,"394a12e"]],"lift":false},{"name":"06_Radio","children":[{"ABF_Smartkey":[[4,"7ff6f33"],[2,"7ead33f"],[1,"c77feb6"],[3,"7ead33f"]]},{"GRD_L":[[4,"76744cd"],[3,"7ead33f"],[1,"7bab0f7"],[2,"7ead33f"]]},[1,"1c40e91"],[2,"7ead33f"],[3,"7ead33f"],[4,"939cfa1"]],"lift":false},{"name":"06_Steering","children":[{"GRD_S":[[4,"2588b5a"],[1,"37c74ac"],[3,"7ead33f"],[2,"7ead33f"]]},[1,"5f39633"],[2,"7ead33f"],[3,"7ead33f"],[4,"eed42ff"]],"lift":false},{"name":"07_Roof","children":[{"ABF_Moonroof":[[2,"53a8134"],{"ICOL_FB01":[[3,"4e9f864"],[1,"7ead33f"],[4,"89b7e42"],[2,"741920d"]]},[4,"5855029"],[1,"7ead33f"],[3,"6fdefc5"]]},{"ICOL_FB01":[[3,"1c8fbae"],[1,"7ead33f"],[2,"18e6749"],[4,"2fd9155"]]},[1,"7ead33f"],[2,"79f0e29"],[3,"d6be9be"],[4,"55cbd65"]],"lift":false},{"name":"06_Seats","children":[{"GRD_eco":[{"ICOL_FB16":[[3,"01f2863"],[1,"27d57ee"],[4,"dfe1aca"],[2,"baaa4e9"]]},{"ICOL_LA22":[[1,"a4557d4"],[3,"6620f73"],[4,"b888e7c"],[2,"fb39eae"]]},{"ICOL_FB41":[[3,"9fce470"],[1,"81e9686"],[2,"c341ab9"],[4,"f309927"]]},{"ICOL_FB01":[[2,"a6ba008"],[1,"e9d6317"],[4,"eb1cc4d"],[3,"34615c8"]]}]},{"GRD_L":[{"ICOL_FA11":[[2,"4536407"],[4,"8eca256"],[1,"e5c0d93"],[3,"a6f74f3"]]}]},{"GRD_S":[{"ICOL_FD22":[[2,"cb95af8"],[3,"f81ef95"],[1,"aad23e2"],[4,"e85d64b"]]},{"ICOL_FD42":[[3,"f107d9e"],[1,"79a3c75"],[4,"9d4cec0"],[2,"02eb943"]]},{"ICOL_LA22":[[4,"55e8a71"],[1,"23dc6bb"],[3,"ac6050b"],[2,"146b116"]]},{"ICOL_FD80":[[4,"7f0aea5"],[3,"fff7ae4"],[2,"53ed2dc"],[1,"aad15c9"]]}]},{"GRD_LE":[{"ICOL_FB01":[[1,"e9d6317"],[3,"34615c8"],[4,"eb1cc4d"],[2,"a6ba008"]]},{"ICOL_LA22":[[4,"b888e7c"],[1,"a4557d4"],[3,"6620f73"],[2,"fb39eae"]]},{"ICOL_FB16":[[2,"baaa4e9"],[3,"01f2863"],[4,"dfe1aca"],[1,"27d57ee"]]},{"ICOL_FB41":[[1,"81e9686"],[2,"c341ab9"],[4,"f309927"],[3,"9fce470"]]}]}],"lift":false},{"name":"05_LightStalk","children":[{"ABF_Foglights":[[3,"7ead33f"],[4,"f094bbb"],[2,"7ead33f"],[1,"1065168"]]},[1,"d195017"],[2,"7ead33f"],[3,"7ead33f"],[4,"fe7796b"]],"lift":false},{"name":"03_DoorPull","children":[{"GRD_L":[[1,"0860c22"],[2,"6023058"],[3,"33340d7"],[4,"582d4d0"]]},[1,"eb77cb3"],[2,"95bd887"],[3,"a4151c5"],[4,"38edfb0"]],"lift":false},{"name":"06_RearviewMirror","children":[[1,"1bcf5f9"],[2,"7ead33f"],[3,"7ead33f"],[4,"216d15f"]],"lift":false},{"name":"06_ParkBrake","children":[{"GRD_L":[[1,"f0475cb"],[2,"7ead33f"],[4,"edb9304"],[3,"7ead33f"]]},[1,"3cec90c"],[2,"7ead33f"],[3,"7ead33f"],[4,"11d2e30"]],"lift":false},{"name":"06_Mode","children":[{"GRD_eco":[[1,"5d29472"],[3,"7ead33f"],[4,"5d77505"],[2,"7ead33f"]]},{"GRD_S":[[2,"7ead33f"],[3,"7ead33f"],[1,"30be113"],[4,"640fafc"]]},[1,"ebc76ab"],[2,"7ead33f"],[3,"7ead33f"],[4,"4c57e1a"]],"lift":false},{"name":"05_Wipers","children":[{"GRD_L":[[4,"45050ce"],[3,"7ead33f"],[2,"7ead33f"],[1,"c881c1f"]]},[1,"4c5f197"],[2,"7ead33f"],[3,"7ead33f"],[4,"a80276c"]],"lift":false},{"name":"06_HeatedSeats","children":[{"ABF_Seatheater":[[2,"7ead33f"],[1,"af1f698"],[3,"7ead33f"],[4,"bf70ca8"]]},[1,"1fef0eb"],[2,"7ead33f"],[3,"7ead33f"],[4,"c4c2d44"]],"lift":false},{"name":"06_ShiftGate","children":[{"TRAN_CVT":[[1,"b3bcbc5"],[4,"47c9293"],[3,"7ead33f"],[2,"7ead33f"]]},{"TRAN_6MT":[[4,"bbfede8"],[3,"7ead33f"],[2,"59e34fd"],[1,"dc3f23f"]]},{"TRAN_4AT":[[3,"7ead33f"],[1,"b1b49c9"],[2,"7ead33f"],[4,"819cdfb"]]}],"lift":false},{"name":"05_RemoteKey","children":[{"GRD_L":[[1,"ec4dad1"],[4,"2de28d3"],[3,"7ead33f"],[2,"7ead33f"]]},[1,"bb9dec4"],[2,"7ead33f"],[3,"7ead33f"],[4,"5bd5d5b"]],"lift":false},{"name":"07_SteeringCntrls","children":[{"GRD_L":[[4,"89a2d09"],[2,"7ead33f"],[3,"7ead33f"],[1,"b1d5308"]]},[1,"7891403"],[2,"7ead33f"],[3,"7ead33f"],[4,"6a43523"]],"lift":false},{"name":"06_CupHolder","children":[{"GRD_L":[[4,"b1e80d0"],[2,"7ead33f"],[1,"493be6b"],[3,"7ead33f"]]},[1,"a1c29e7"],[2,"7ead33f"],[3,"7ead33f"],[4,"64fb863"]],"lift":false},{"name":"05_AC","children":[{"GRD_L":[[4,"7e3152e"],[3,"7ead33f"],[2,"7ead33f"],[1,"782296a"]]},[1,"c4b2de6"],[2,"7ead33f"],[3,"7ead33f"],[4,"1b41612"]],"lift":false},{"name":"01_Background","children":[[2,"a0f4d0d"],[4,"cd857a7"],[1,"e2c25b7"],[3,"bb20489"]],"lift":false},{"name":"05_SmartKey","children":[{"ABF_Smartkey":[[4,"1cf9818"],[3,"7ead33f"],[2,"7ead33f"],[1,"97b79f3"]]},[1,"25e1344"],[2,"7ead33f"],[3,"7ead33f"],[4,"8dc07cc"]],"lift":false}]}],"profileMap":{"599_366_JPG":{"baseImageType":"JPG","imageSize":{"w":599,"h":366}},"480_293_JPG":{"baseImageType":"JPG","imageSize":{"w":480,"h":293}},"960_530_PNG":{"baseImageType":"PNG","imageSize":{"w":960,"h":530}},"680_383_PNG":{"baseImageType":"PNG","imageSize":{"w":680,"h":383}},"380_214_PNG":{"baseImageType":"PNG","imageSize":{"w":380,"h":214}},"864_477_PNG":{"baseImageType":"PNG","imageSize":{"w":864,"h":477}}},"key":"toyota/1000851/1000855"}